Workbook
Name NativeTimeline_Order_Date: #N/A
Name Slicer_Order_Status: #N/A
Name Slicer_Product_Category1: #N/A
Name Slicer_Region: #N/A

Sheet Dashboard
A1: E-Commerce Sales Analytics

Sheet sales_data_original
A1: Order_ID | B1: Order_Date | C1: Customer_Name | D1: Customer_Email | E1: Region | F1: City | G1: Product_Category | H1: Product_Name | I1: Quantity | J1: Unit_Price | K1: Discount_Percent | L1: Shipping_Cost | M1: Payment_Method | N1: Order_Status
A2: ORD-1001 | B2: 45296 | C2: John Smith | D2: john.smith@email.com | E2: North | F2: New York | G2: Electronics | H2: Wireless Mouse | I2: 2 | J2: 29.99 | K2: 10 | L2: 5.99 | M2: Credit Card | N2: Delivered
A3: ORD-1002 | B3: 45298 | C3: Sarah Johnson | D3: sarah.j@email.com | E3: South | F3: Miami | G3: Home & Garden | H3: Plant Pot Set | I3: 1 | J3: 45.5 | K3: 0 | L3: 7.5 | M3: PayPal | N3: Delivered
A4: ORD-1003 | B4: 45299 | C4: Michael Brown | D4: m.brown@email.com | E4: East | F4: Boston | G4: Electronics | H4: USB Cable | I4: 5 | J4: 12.99 | K4: 15 | L4: 4.99 | M4: Credit Card | N4: Delivered
A5: ORD-1004 | B5: 45301 | C5: Emily Davis | D5: emily.d@email.com | E5: West | F5: Los Angeles | G5: Clothing | H5: Cotton T-Shirt | I5: 3 | J5: 19.99 | K5: 20 | L5: 6.5 | M5: Debit Card | N5: Delivered
A6: ORD-1005 | B6: 45303 | C6: David Wilson | D6: d.wilson@email.com | E6: North | F6: Chicago | G6: Electronics | H6: Keyboard | I6: 1 | J6: 89.99 | K6: 5 | L6: 8.99 | M6: Credit Card | N6: Delivered
A7: ORD-1006 | B7: 45306 | C7: Lisa Anderson | D7: lisa.a@email.com | E7: South | F7: Houston | G7: Home & Garden | H7: Garden Tools | I7: 2 | J7: 34.99 | K7: 0 | L7: 9.99 | M7: PayPal | N7: Delivered
A8: ORD-1007 | B8: 45309 | C8: James Martinez | D8: james.m@email.com | E8: East | F8: Philadelphia | G8: Books | H8: Programming Guide | I8: 1 | J8: 54.99 | K8: 10 | L8: 3.99 | M8: Credit Card | N8: Cancelled
A9: ORD-1008 | B9: 45311 | C9: Patricia Taylor | D9: patricia.t@email.com | E9: West | F9: San Francisco | G9: Clothing | H9: Denim Jeans | I9: 2 | J9: 59.99 | K9: 15 | L9: 7.99 | M9: Credit Card | N9: Delivered
A10: ORD-1009 | B10: 45313 | C10: Robert Thomas | D10: robert.t@email.com | E10: North | F10: Detroit | G10: Electronics | H10: Webcam | I10: 1 | J10: 79.99 | K10: 0 | L10: 6.5 | M10: Debit Card | N10: Processing
A11: ORD-1010 | B11: 45316 | C11: Jennifer Lee | D11: jennifer.l@email.com | E11: South | F11: Atlanta | G11: Books | H11: Business Strategy | I11: 2 | J11: 39.99 | K11: 5 | L11: 4.5 | M11: PayPal | N11: Delivered
A12: ORD-1011 | B12: 45319 | C12: William White | D12: william.w@email.com | E12: East | F12: New York | G12: Electronics | H12: Laptop Stand | I12: 1 | J12: 49.99 | K12: 10 | L12: 8.5 | M12: Credit Card | N12: Delivered
A13: ORD-1012 | B13: 45323 | C13: Mary Harris | D13: mary.h@email.com | E13: West | F13: Seattle | G13: Home & Garden | H13: Decorative Vase | I13: 3 | J13: 24.99 | K13: 0 | L13: 5.99 | M13: PayPal | N13: Delivered
... A101: ORD-1100 | B101: 45545 | C101: Norma Jordan | D101: norma.j@email.com | E101: West | F101: Los Angeles | G101: Books | H101: Educational | I101: 2 | J101: 44.99 | K101: 10 | L101: 5.5 | M101: Credit Card | N101: Delivered

Sheet sales_data
A1: Order_ID | B1: Order_Date | C1: Month | D1: Customer_Name | E1: Customer_Email | F1: Region | G1: City | H1: Product_Category | I1: Product_Name | J1: Quantity | K1: Unit_Price | L1: Subtotal | M1: Discount_Percent | N1: Discount_Amount | O1: Net_Amount | P1: Shipping_Cost | Q1: Total Order Value | R1: Revenue Category | S1: Payment_Method | T1: Order_Status
A2: ORD-1037 | B2: 45385 | C2: =TEXT(SalesData[[#This Row],[Order_Date]],"MMMM") -> April | D2: Justin Edwards | E2: justin.e@email.com | F2: North | G2: Minneapolis | H2: Books | I2: Cookbook | J2: 1 | K2: 34.99 | L2: =SalesData[[#This Row],[Unit_Price]]*SalesData[[#This Row],[Quantity]] -> 34.99 | M2: 5 | N2: =SalesData[[#This Row],[Subtotal]]*(SalesData[[#This Row],[Discount_Percent]]/100) -> 1.7495 | O2: =SalesData[[#This Row],[Subtotal]]-SalesData[[#This Row],[Discount_Amount]] -> 33.2405 | P2: 3.99 | Q2: =SUM(SalesData[[#This Row],[Net_Amount]]+SalesData[[#This Row],[Shipping_Cost]]) -> 37.2305 | R2: =IF(SalesData[[#This Row],[Total Order Value]]>200,"High Value",IF(SalesData[[#This Row],[Total Order Value]]>100,"Medium Value","Low Value")) -> Low Value | S2: Debit Card | T2: Delivered
A3: ORD-1049 | B3: 45415 | C3: =TEXT(SalesData[[#This Row],[Order_Date]],"MMMM") -> May | D3: Gregory Cooper | E3: gregory.c@email.com | F3: North | G3: Minneapolis | H3: Clothing | I3: Track Pants | J3: 1 | K3: 44.99 | L3: =SalesData[[#This Row],[Unit_Price]]*SalesData[[#This Row],[Quantity]] -> 44.99 | M3: 25 | N3: =SalesData[[#This Row],[Subtotal]]*(SalesData[[#This Row],[Discount_Percent]]/100) -> 11.2475 | O3: =SalesData[[#This Row],[Subtotal]]-SalesData[[#This Row],[Discount_Amount]] -> 33.7425 | P3: 6.5 | Q3: =SUM(SalesData[[#This Row],[Net_Amount]]+SalesData[[#This Row],[Shipping_Cost]]) -> 40.2425 | R3: =IF(SalesData[[#This Row],[Total Order Value]]>200,"High Value",IF(SalesData[[#This Row],[Total Order Value]]>100,"Medium Value","Low Value")) -> Low Value | S3: PayPal | T3: Delivered
A4: ORD-1021 | B4: 45344 | C4: =TEXT(SalesData[[#This Row],[Order_Date]],"MMMM") -> February | D4: Joseph Lopez | E4: joseph.l@email.com | F4: North | G4: Detroit | H4: Home & Garden | I4: Wall Clock | J4: 1 | K4: 39.99 | L4: =SalesData[[#This Row],[Unit_Price]]*SalesData[[#This Row],[Quantity]] -> 39.99 | M4: 10 | N4: =SalesData[[#This Row],[Subtotal]]*(SalesData[[#This Row],[Discount_Percent]]/100) -> 3.999 | O4: =SalesData[[#This Row],[Subtotal]]-SalesData[[#This Row],[Discount_Amount]] -> 35.991 | P4: 5.99 | Q4: =SUM(SalesData[[#This Row],[Net_Amount]]+SalesData[[#This Row],[Shipping_Cost]]) -> 41.981 | R4: =IF(SalesData[[#This Row],[Total Order Value]]>200,"High Value",IF(SalesData[[#This Row],[Total Order Value]]>100,"Medium Value","Low Value")) -> Low Value | S4: Credit Card | T4: Delivered
A5: ORD-1069 | B5: 45465 | C5: =TEXT(SalesData[[#This Row],[Order_Date]],"MMMM") -> June | D5: Roger Coleman | E5: roger.c@email.com | F5: North | G5: Detroit | H5: Books | I5: Philosophy | J5: 1 | K5: 44.99 | L5: =SalesData[[#This Row],[Unit_Price]]*SalesData[[#This Row],[Quantity]] -> 44.99 | M5: 0 | N5: =SalesData[[#This Row],[Subtotal]]*(SalesData[[#This Row],[Discount_Percent]]/100) -> 0 | O5: =SalesData[[#This Row],[Subtotal]]-SalesData[[#This Row],[Discount_Amount]] -> 44.99 | P5: 4.5 | Q5: =SUM(SalesData[[#This Row],[Net_Amount]]+SalesData[[#This Row],[Shipping_Cost]]) -> 49.49 | R5: =IF(SalesData[[#This Row],[Total Order Value]]>200,"High Value",IF(SalesData[[#This Row],[Total Order Value]]>100,"Medium Value","Low Value")) -> Low Value | S5: Credit Card | T5: Delivered
A6: ORD-1073 | B6: 45476 | C6: =TEXT(SalesData[[#This Row],[Order_Date]],"MMMM") -> July | D6: Arthur Long | E6: arthur.l@email.com | F6: North | G6: Minneapolis | H6: Books | I6: Poetry | J6: 2 | K6: 24.99 | L6: =SalesData[[#This Row],[Unit_Price]]*SalesData[[#This Row],[Quantity]] -> 49.98 | M6: 0 | N6: =SalesData[[#This Row],[Subtotal]]*(SalesData[[#This Row],[Discount_Percent]]/100) -> 0 | O6: =SalesData[[#This Row],[Subtotal]]-SalesData[[#This Row],[Discount_Amount]] -> 49.98 | P6: 3.99 | Q6: =SUM(SalesData[[#This Row],[Net_Amount]]+SalesData[[#This Row],[Shipping_Cost]]) -> 53.97 | R6: =IF(SalesData[[#This Row],[Total Order Value]]>200,"High Value",IF(SalesData[[#This Row],[Total Order Value]]>100,"Medium Value","Low Value")) -> Low Value | S6: PayPal | T6: Delivered
A7: ORD-1033 | B7: 45373 | C7: =TEXT(SalesData[[#This Row],[Order_Date]],"MMMM") -> March | D7: Jason Phillips | E7: jason.p@email.com | F7: North | G7: Detroit | H7: Books | I7: History Book | J7: 1 | K7: 49.99 | L7: =SalesData[[#This Row],[Unit_Price]]*SalesData[[#This Row],[Quantity]] -> 49.99 | M7: 0 | N7: =SalesData[[#This Row],[Subtotal]]*(SalesData[[#This Row],[Discount_Percent]]/100) -> 0 | O7: =SalesData[[#This Row],[Subtotal]]-SalesData[[#This Row],[Discount_Amount]] -> 49.99 | P7: 4.99 | Q7: =SUM(SalesData[[#This Row],[Net_Amount]]+SalesData[[#This Row],[Shipping_Cost]]) -> 54.98 | R7: =IF(SalesData[[#This Row],[Total Order Value]]>200,"High Value",IF(SalesData[[#This Row],[Total Order Value]]>100,"Medium Value","Low Value")) -> Low Value | S7: Debit Card | T7: Delivered
A8: ORD-1081 | B8: 45495 | C8: =TEXT(SalesData[[#This Row],[Order_Date]],"MMMM") -> July | D8: Russell Gonzales | E8: russell.g@email.com | F8: North | G8: Detroit | H8: Clothing | I8: Gloves | J8: 4 | K8: 14.99 | L8: =SalesData[[#This Row],[Unit_Price]]*SalesData[[#This Row],[Quantity]] -> 59.96 | M8: 10 | N8: =SalesData[[#This Row],[Subtotal]]*(SalesData[[#This Row],[Discount_Percent]]/100) -> 5.996 | O8: =SalesData[[#This Row],[Subtotal]]-SalesData[[#This Row],[Discount_Amount]] -> 53.964 | P8: 4.5 | Q8: =SUM(SalesData[[#This Row],[Net_Amount]]+SalesData[[#This Row],[Shipping_Cost]]) -> 58.464 | R8: =IF(SalesData[[#This Row],[Total Order Value]]>200,"High Value",IF(SalesData[[#This Row],[Total Order Value]]>100,"Medium Value","Low Value")) -> Low Value | S8: Credit Card | T8: Delivered
A9: ORD-1001 | B9: 45296 | C9: =TEXT(SalesData[[#This Row],[Order_Date]],"MMMM") -> January | D9: John Smith | E9: john.smith@email.com | F9: North | G9: New York | H9: Electronics | I9: Wireless Mouse | J9: 2 | K9: 29.99 | L9: =SalesData[[#This Row],[Unit_Price]]*SalesData[[#This Row],[Quantity]] -> 59.98 | M9: 10 | N9: =SalesData[[#This Row],[Subtotal]]*(SalesData[[#This Row],[Discount_Percent]]/100) -> 5.998 | O9: =SalesData[[#This Row],[Subtotal]]-SalesData[[#This Row],[Discount_Amount]] -> 53.982 | P9: 5.99 | Q9: =SUM(SalesData[[#This Row],[Net_Amount]]+SalesData[[#This Row],[Shipping_Cost]]) -> 59.972 | R9: =IF(SalesData[[#This Row],[Total Order Value]]>200,"High Value",IF(SalesData[[#This Row],[Total Order Value]]>100,"Medium Value","Low Value")) -> Low Value | S9: Credit Card | T9: Delivered
A10: ORD-1061 | B10: 45446 | C10: =TEXT(SalesData[[#This Row],[Order_Date]],"MMMM") -> June | D10: Walter Kelly | E10: walter.k@email.com | F10: North | G10: Minneapolis | H10: Home & Garden | I10: Coat Rack | J10: 1 | K10: 69.99 | L10: =SalesData[[#This Row],[Unit_Price]]*SalesData[[#This Row],[Quantity]] -> 69.99 | M10: 15 | N10: =SalesData[[#This Row],[Subtotal]]*(SalesData[[#This Row],[Discount_Percent]]/100) -> 10.4985 | O10: =SalesData[[#This Row],[Subtotal]]-SalesData[[#This Row],[Discount_Amount]] -> 59.4915 | P10: 8.99 | Q10: =SUM(SalesData[[#This Row],[Net_Amount]]+SalesData[[#This Row],[Shipping_Cost]]) -> 68.4815 | R10: =IF(SalesData[[#This Row],[Total Order Value]]>200,"High Value",IF(SalesData[[#This Row],[Total Order Value]]>100,"Medium Value","Low Value")) -> Low Value | S10: Debit Card | T10: Delivered
A11: ORD-1053 | B11: 45424 | C11: =TEXT(SalesData[[#This Row],[Order_Date]],"MMMM") -> May | D11: Jonathan Ward | E11: jonathan.w@email.com | F11: North | G11: Chicago | H11: Electronics | I11: Screen Protector | J11: 5 | K11: 14.99 | L11: =SalesData[[#This Row],[Unit_Price]]*SalesData[[#This Row],[Quantity]] -> 74.95 | M11: 10 | N11: =SalesData[[#This Row],[Subtotal]]*(SalesData[[#This Row],[Discount_Percent]]/100) -> 7.495 | O11: =SalesData[[#This Row],[Subtotal]]-SalesData[[#This Row],[Discount_Amount]] -> 67.455 | P11: 2.99 | Q11: =SUM(SalesData[[#This Row],[Net_Amount]]+SalesData[[#This Row],[Shipping_Cost]]) -> 70.445 | R11: =IF(SalesData[[#This Row],[Total Order Value]]>200,"High Value",IF(SalesData[[#This Row],[Total Order Value]]>100,"Medium Value","Low Value")) -> Low Value | S11: Credit Card | T11: Processing | Y11: Regions | Z11: Order_Status
A12: ORD-1093 | B12: 45526 | C12: =TEXT(SalesData[[#This Row],[Order_Date]],"MMMM") -> August | D12: Henry Wallace | E12: henry.w@email.com | F12: North | G12: Detroit | H12: Home & Garden | I12: Key Holder | J12: 4 | K12: 17.99 | L12: =SalesData[[#This Row],[Unit_Price]]*SalesData[[#This Row],[Quantity]] -> 71.96 | M12: 5 | N12: =SalesData[[#This Row],[Subtotal]]*(SalesData[[#This Row],[Discount_Percent]]/100) -> 3.598 | O12: =SalesData[[#This Row],[Subtotal]]-SalesData[[#This Row],[Discount_Amount]] -> 68.362 | P12: 4.5 | Q12: =SUM(SalesData[[#This Row],[Net_Amount]]+SalesData[[#This Row],[Shipping_Cost]]) -> 72.862 | R12: =IF(SalesData[[#This Row],[Total Order Value]]>200,"High Value",IF(SalesData[[#This Row],[Total Order Value]]>100,"Medium Value","Low Value")) -> Low Value | S12: Debit Card | T12: Cancelled | Y12: North | Z12: Delivered
A13: ORD-1065 | B13: 45455 | C13: =TEXT(SalesData[[#This Row],[Order_Date]],"MMMM") -> June | D13: Gerald Wood | E13: gerald.w@email.com | F13: North | G13: Chicago | H13: Electronics | I13: Cable Organizer | J13: 6 | K13: 12.99 | L13: =SalesData[[#This Row],[Unit_Price]]*SalesData[[#This Row],[Quantity]] -> 77.94 | M13: 5 | N13: =SalesData[[#This Row],[Subtotal]]*(SalesData[[#This Row],[Discount_Percent]]/100) -> 3.897 | O13: =SalesData[[#This Row],[Subtotal]]-SalesData[[#This Row],[Discount_Amount]] -> 74.043 | P13: 2.99 | Q13: =SUM(SalesData[[#This Row],[Net_Amount]]+SalesData[[#This Row],[Shipping_Cost]]) -> 77.033 | R13: =IF(SalesData[[#This Row],[Total Order Value]]>200,"High Value",IF(SalesData[[#This Row],[Total Order Value]]>100,"Medium Value","Low Value")) -> Low Value | S13: Debit Card | T13: Cancelled | Y13: South | Z13: Processing
A14: ORD-1041 | B14: 45394 | C14: =TEXT(SalesData[[#This Row],[Order_Date]],"MMMM") -> April | D14: Eric Rogers | E14: eric.r@email.com | F14: North | G14: Chicago | H14: Electronics | I14: Power Bank | J14: 2 | K14: 44.99 | L14: =SalesData[[#This Row],[Unit_Price]]*SalesData[[#This Row],[Quantity]] -> 89.98 | M14: 15 | N14: =SalesData[[#This Row],[Subtotal]]*(SalesData[[#This Row],[Discount_Percent]]/100) -> 13.497 | O14: =SalesData[[#This Row],[Subtotal]]-SalesData[[#This Row],[Discount_Amount]] -> 76.483 | P14: 5.5 | Q14: =SUM(SalesData[[#This Row],[Net_Amount]]+SalesData[[#This Row],[Shipping_Cost]]) -> 81.983 | R14: =IF(SalesData[[#This Row],[Total Order Value]]>200,"High Value",IF(SalesData[[#This Row],[Total Order Value]]>100,"Medium Value","Low Value")) -> Low Value | S14: Credit Card | T14: Delivered | Y14: East | Z14: Cancelled
A15: ORD-1097 | B15: 45538 | C15: =TEXT(SalesData[[#This Row],[Order_Date]],"MMMM") -> September | D15: Joe Newman | E15: joe.n@email.com | F15: North | G15: Minneapolis | H15: Home & Garden | I15: Mirror | J15: 1 | K15: 89.99 | L15: =SalesData[[#This Row],[Unit_Price]]*SalesData[[#This Row],[Quantity]] -> 89.99 | M15: 20 | N15: =SalesData[[#This Row],[Subtotal]]*(SalesData[[#This Row],[Discount_Percent]]/100) -> 17.998 | O15: =SalesData[[#This Row],[Subtotal]]-SalesData[[#This Row],[Discount_Amount]] -> 71.992 | P15: 11.99 | Q15: =SUM(SalesData[[#This Row],[Net_Amount]]+SalesData[[#This Row],[Shipping_Cost]]) -> 83.982 | R15: =IF(SalesData[[#This Row],[Total Order Value]]>200,"High Value",IF(SalesData[[#This Row],[Total Order Value]]>100,"Medium Value","Low Value")) -> Low Value | S15: Credit Card | T15: Delivered | Y15: West
A16: ORD-1009 | B16: 45313 | C16: =TEXT(SalesData[[#This Row],[Order_Date]],"MMMM") -> January | D16: Robert Thomas | E16: robert.t@email.com | F16: North | G16: Detroit | H16: Electronics | I16: Webcam | J16: 1 | K16: 79.99 | L16: =SalesData[[#This Row],[Unit_Price]]*SalesData[[#This Row],[Quantity]] -> 79.99 | M16: 0 | N16: =SalesData[[#This Row],[Subtotal]]*(SalesData[[#This Row],[Discount_Percent]]/100) -> 0 | O16: =SalesData[[#This Row],[Subtotal]]-SalesData[[#This Row],[Discount_Amount]] -> 79.99 | P16: 6.5 | Q16: =SUM(SalesData[[#This Row],[Net_Amount]]+SalesData[[#This Row],[Shipping_Cost]]) -> 86.49 | R16: =IF(SalesData[[#This Row],[Total Order Value]]>200,"High Value",IF(SalesData[[#This Row],[Total Order Value]]>100,"Medium Value","Low Value")) -> Low Value | S16: Debit Card | T16: Processing
A17: ORD-1077 | B17: 45485 | C17: =TEXT(SalesData[[#This Row],[Order_Date]],"MMMM") -> July | D17: Louis Washington | E17: louis.w@email.com | F17: North | G17: Chicago | H17: Electronics | I17: Car Charger | J17: 5 | K17: 19.99 | L17: =SalesData[[#This Row],[Unit_Price]]*SalesData[[#This Row],[Quantity]] -> 99.95 | M17: 15 | N17: =SalesData[[#This Row],[Subtotal]]*(SalesData[[#This Row],[Discount_Percent]]/100) -> 14.9925 | O17: =SalesData[[#This Row],[Subtotal]]-SalesData[[#This Row],[Discount_Amount]] -> 84.9575 | P17: 3.99 | Q17: =SUM(SalesData[[#This Row],[Net_Amount]]+SalesData[[#This Row],[Shipping_Cost]]) -> 88.9475 | R17: =IF(SalesData[[#This Row],[Total Order Value]]>200,"High Value",IF(SalesData[[#This Row],[Total Order Value]]>100,"Medium Value","Low Value")) -> Low Value | S17: PayPal | T17: Delivered
A18: ORD-1057 | B18: 45434 | C18: =TEXT(SalesData[[#This Row],[Order_Date]],"MMMM") -> May | D18: Dennis Ramirez | E18: dennis.r@email.com | F18: North | G18: Detroit | H18: Home & Garden | I18: Floor Mat | J18: 3 | K18: 29.99 | L18: =SalesData[[#This Row],[Unit_Price]]*SalesData[[#This Row],[Quantity]] -> 89.97 | M18: 5 | N18: =SalesData[[#This Row],[Subtotal]]*(SalesData[[#This Row],[Discount_Percent]]/100) -> 4.4985 | O18: =SalesData[[#This Row],[Subtotal]]-SalesData[[#This Row],[Discount_Amount]] -> 85.4715 | P18: 5.99 | Q18: =SUM(SalesData[[#This Row],[Net_Amount]]+SalesData[[#This Row],[Shipping_Cost]]) -> 91.4615 | R18: =IF(SalesData[[#This Row],[Total Order Value]]>200,"High Value",IF(SalesData[[#This Row],[Total Order Value]]>100,"Medium Value","Low Value")) -> Low Value | S18: Credit Card | T18: Delivered
A19: ORD-1005 | B19: 45303 | C19: =TEXT(SalesData[[#This Row],[Order_Date]],"MMMM") -> January | D19: David Wilson | E19: d.wilson@email.com | F19: North | G19: Chicago | H19: Electronics | I19: Keyboard | J19: 1 | K19: 89.99 | L19: =SalesData[[#This Row],[Unit_Price]]*SalesData[[#This Row],[Quantity]] -> 89.99 | M19: 5 | N19: =SalesData[[#This Row],[Subtotal]]*(SalesData[[#This Row],[Discount_Percent]]/100) -> 4.4995 | O19: =SalesData[[#This Row],[Subtotal]]-SalesData[[#This Row],[Discount_Amount]] -> 85.4905 | P19: 8.99 | Q19: =SUM(SalesData[[#This Row],[Net_Amount]]+SalesData[[#This Row],[Shipping_Cost]]) -> 94.4805 | R19: =IF(SalesData[[#This Row],[Total Order Value]]>200,"High Value",IF(SalesData[[#This Row],[Total Order Value]]>100,"Medium Value","Low Value")) -> Low Value | S19: Credit Card | T19: Delivered
A20: ORD-1085 | B20: 45507 | C20: =TEXT(SalesData[[#This Row],[Order_Date]],"MMMM") -> August | D20: Randy Griffin | E20: randy.g@email.com | F20: North | G20: Minneapolis | H20: Clothing | I20: Socks Pack | J20: 6 | K20: 19.99 | L20: =SalesData[[#This Row],[Unit_Price]]*SalesData[[#This Row],[Quantity]] -> 119.94 | M20: 25 | N20: =SalesData[[#This Row],[Subtotal]]*(SalesData[[#This Row],[Discount_Percent]]/100) -> 29.985 | O20: =SalesData[[#This Row],[Subtotal]]-SalesData[[#This Row],[Discount_Amount]] -> 89.955 | P20: 4.99 | Q20: =SUM(SalesData[[#This Row],[Net_Amount]]+SalesData[[#This Row],[Shipping_Cost]]) -> 94.945 | R20: =IF(SalesData[[#This Row],[Total Order Value]]>200,"High Value",IF(SalesData[[#This Row],[Total Order Value]]>100,"Medium Value","Low Value")) -> Low Value | S20: Credit Card | T20: Delivered
A21: ORD-1045 | B21: 45404 | C21: =TEXT(SalesData[[#This Row],[Order_Date]],"MMMM") -> April | D21: Nicholas Bell | E21: nicholas.b@email.com | F21: North | G21: Detroit | H21: Clothing | I21: Sweatshirt | J21: 2 | K21: 54.99 | L21: =SalesData[[#This Row],[Unit_Price]]*SalesData[[#This Row],[Quantity]] -> 109.98 | M21: 20 | N21: =SalesData[[#This Row],[Subtotal]]*(SalesData[[#This Row],[Discount_Percent]]/100) -> 21.996 | O21: =SalesData[[#This Row],[Subtotal]]-SalesData[[#This Row],[Discount_Amount]] -> 87.984 | P21: 7.99 | Q21: =SUM(SalesData[[#This Row],[Net_Amount]]+SalesData[[#This Row],[Shipping_Cost]]) -> 95.974 | R21: =IF(SalesData[[#This Row],[Total Order Value]]>200,"High Value",IF(SalesData[[#This Row],[Total Order Value]]>100,"Medium Value","Low Value")) -> Low Value | S21: PayPal | T21: Processing
A22: ORD-1029 | B22: 45363 | C22: =TEXT(SalesData[[#This Row],[Order_Date]],"MMMM") -> March | D22: George Mitchell | E22: george.m@email.com | F22: North | G22: Chicago | H22: Electronics | I22: External Hard Drive | J22: 1 | K22: 119.99 | L22: =SalesData[[#This Row],[Unit_Price]]*SalesData[[#This Row],[Quantity]] -> 119.99 | M22: 15 | N22: =SalesData[[#This Row],[Subtotal]]*(SalesData[[#This Row],[Discount_Percent]]/100) -> 17.9985 | O22: =SalesData[[#This Row],[Subtotal]]-SalesData[[#This Row],[Discount_Amount]] -> 101.9915 | P22: 9.99 | Q22: =SUM(SalesData[[#This Row],[Net_Amount]]+SalesData[[#This Row],[Shipping_Cost]]) -> 111.9815 | R22: =IF(SalesData[[#This Row],[Total Order Value]]>200,"High Value",IF(SalesData[[#This Row],[Total Order Value]]>100,"Medium Value","Low Value")) -> Medium Value | S22: Credit Card | T22: Delivered
A23: ORD-1013 | B23: 45325 | C23: =TEXT(SalesData[[#This Row],[Order_Date]],"MMMM") -> February | D23: Christopher Clark | E23: chris.c@email.com | F23: North | G23: Minneapolis | H23: Clothing | I23: Winter Jacket | J23: 1 | K23: 129.99 | L23: =SalesData[[#This Row],[Unit_Price]]*SalesData[[#This Row],[Quantity]] -> 129.99 | M23: 20 | N23: =SalesData[[#This Row],[Subtotal]]*(SalesData[[#This Row],[Discount_Percent]]/100) -> 25.998 | O23: =SalesData[[#This Row],[Subtotal]]-SalesData[[#This Row],[Discount_Amount]] -> 103.992 | P23: 12.99 | Q23: =SUM(SalesData[[#This Row],[Net_Amount]]+SalesData[[#This Row],[Shipping_Cost]]) -> 116.982 | R23: =IF(SalesData[[#This Row],[Total Order Value]]>200,"High Value",IF(SalesData[[#This Row],[Total Order Value]]>100,"Medium Value","Low Value")) -> Medium Value | S23: Credit Card | T23: Delivered
A24: ORD-1025 | B24: 45354 | C24: =TEXT(SalesData[[#This Row],[Order_Date]],"MMMM") -> March | D24: Paul Adams | E24: paul.a@email.com | F24: North | G24: Minneapolis | H24: Home & Garden | I24: Cushion Set | J24: 2 | K24: 54.99 | L24: =SalesData[[#This Row],[Unit_Price]]*SalesData[[#This Row],[Quantity]] -> 109.98 | M24: 0 | N24: =SalesData[[#This Row],[Subtotal]]*(SalesData[[#This Row],[Discount_Percent]]/100) -> 0 | O24: =SalesData[[#This Row],[Subtotal]]-SalesData[[#This Row],[Discount_Amount]] -> 109.98 | P24: 8.5 | Q24: =SUM(SalesData[[#This Row],[Net_Amount]]+SalesData[[#This Row],[Shipping_Cost]]) -> 118.48 | R24: =IF(SalesData[[#This Row],[Total Order Value]]>200,"High Value",IF(SalesData[[#This Row],[Total Order Value]]>100,"Medium Value","Low Value")) -> Medium Value | S24: Credit Card | T24: Delivered
A25: ORD-1017 | B25: 45334 | C25: =TEXT(SalesData[[#This Row],[Order_Date]],"MMMM") -> February | D25: Matthew Allen | E25: matt.a@email.com | F25: North | G25: Chicago | H25: Electronics | I25: Monitor | J25: 1 | K25: 299.99 | L25: =SalesData[[#This Row],[Unit_Price]]*SalesData[[#This Row],[Quantity]] -> 299.99 | M25: 10 | N25: =SalesData[[#This Row],[Subtotal]]*(SalesData[[#This Row],[Discount_Percent]]/100) -> 29.999 | O25: =SalesData[[#This Row],[Subtotal]]-SalesData[[#This Row],[Discount_Amount]] -> 269.991 | P25: 15.99 | Q25: =SUM(SalesData[[#This Row],[Net_Amount]]+SalesData[[#This Row],[Shipping_Cost]]) -> 285.981 | R25: =IF(SalesData[[#This Row],[Total Order Value]]>200,"High Value",IF(SalesData[[#This Row],[Total Order Value]]>100,"Medium Value","Low Value")) -> High Value | S25: Credit Card | T25: Delivered
A26: ORD-1089 | B26: 45516 | C26: =TEXT(SalesData[[#This Row],[Order_Date]],"MMMM") -> August | D26: Jack Ford | E26: jack.f@email.com | F26: North | G26: Chicago | H26: Electronics | I26: VR Headset | J26: 1 | K26: 399.99 | L26: =SalesData[[#This Row],[Unit_Price]]*SalesData[[#This Row],[Quantity]] -> 399.99 | M26: 20 | N26: =SalesData[[#This Row],[Subtotal]]*(SalesData[[#This Row],[Discount_Percent]]/100) -> 79.998 | O26: =SalesData[[#This Row],[Subtotal]]-SalesData[[#This Row],[Discount_Amount]] -> 319.992 | P26: 19.99 | Q26: =SUM(SalesData[[#This Row],[Net_Amount]]+SalesData[[#This Row],[Shipping_Cost]]) -> 339.982 | R26: =IF(SalesData[[#This Row],[Total Order Value]]>200,"High Value",IF(SalesData[[#This Row],[Total Order Value]]>100,"Medium Value","Low Value")) -> High Value | S26: Debit Card | T26: Delivered
A27: ORD-1066 | B27: 45458 | C27: =TEXT(SalesData[[#This Row],[Order_Date]],"MMMM") -> June | D27: Judith Barnes | E27: judith.b@email.com | F27: South | G27: Miami | H27: Home & Garden | I27: Napkin Holder | J27: 2 | K27: 24.99 | L27: =SalesData[[#This Row],[Unit_Price]]*SalesData[[#This Row],[Quantity]] -> 49.98 | M27: 15 | N27: =SalesData[[#This Row],[Subtotal]]*(SalesData[[#This Row],[Discount_Percent]]/100) -> 7.497 | O27: =SalesData[[#This Row],[Subtotal]]-SalesData[[#This Row],[Discount_Amount]] -> 42.483 | P27: 5.5 | Q27: =SUM(SalesData[[#This Row],[Net_Amount]]+SalesData[[#This Row],[Shipping_Cost]]) -> 47.983 | R27: =IF(SalesData[[#This Row],[Total Order Value]]>200,"High Value",IF(SalesData[[#This Row],[Total Order Value]]>100,"Medium Value","Low Value")) -> Low Value | S27: PayPal | T27: Delivered
... A101: ORD-1092 | B101: 45524 | C101: =TEXT(SalesData[[#This Row],[Order_Date]],"MMMM") -> August | D101: Martha Sullivan | E101: martha.s@email.com | F101: West | G101: San Francisco | H101: Electronics | I101: Smart Doorbell | J101: 1 | K101: 179.99 | L101: =SalesData[[#This Row],[Unit_Price]]*SalesData[[#This Row],[Quantity]] -> 179.99 | M101: 15 | N101: =SalesData[[#This Row],[Subtotal]]*(SalesData[[#This Row],[Discount_Percent]]/100) -> 26.9985 | O101: =SalesData[[#This Row],[Subtotal]]-SalesData[[#This Row],[Discount_Amount]] -> 152.9915 | P101: 12.99 | Q101: =SUM(SalesData[[#This Row],[Net_Amount]]+SalesData[[#This Row],[Shipping_Cost]]) -> 165.9815 | R101: =IF(SalesData[[#This Row],[Total Order Value]]>200,"High Value",IF(SalesData[[#This Row],[Total Order Value]]>100,"Medium Value","Low Value")) -> Medium Value | S101: Credit Card | T101: Delivered

Sheet sorted_analysis
A1: Order_ID | B1: Order_Date | C1: Month | D1: Customer_Name | E1: Customer_Email | F1: Region | G1: City | H1: Product_Category | I1: Product_Name | J1: Quantity | K1: Unit_Price | L1: Subtotal | M1: Discount_Percent | N1: Discount_Amount | O1: Net_Amount | P1: Shipping_Cost | Q1: Total Order Value | R1: Revenue Category | S1: Payment_Method | T1: Order_Status
A2: ORD-1037 | B2: 45385 | C2: =TEXT(sorted_analysis!$B2,"MMMM") -> April | D2: Justin Edwards | E2: justin.e@email.com | F2: North | G2: Minneapolis | H2: Books | I2: Cookbook | J2: 1 | K2: 34.99 | L2: =sorted_analysis!$K2*sorted_analysis!$J2 -> 34.99 | M2: 5 | N2: =sorted_analysis!$L2*(sorted_analysis!$M2/100) -> 1.7495 | O2: =sorted_analysis!$L2-sorted_analysis!$N2 -> 33.2405 | P2: 3.99 | Q2: =SUM(sorted_analysis!$O2+sorted_analysis!$P2) -> 37.2305 | R2: =IF(sorted_analysis!$Q2>200,"High Value",IF(sorted_analysis!$Q2>100,"Medium Value","Low Value")) -> Low Value | S2: Debit Card | T2: Delivered
A3: ORD-1049 | B3: 45415 | C3: =TEXT(sorted_analysis!$B3,"MMMM") -> May | D3: Gregory Cooper | E3: gregory.c@email.com | F3: North | G3: Minneapolis | H3: Clothing | I3: Track Pants | J3: 1 | K3: 44.99 | L3: =sorted_analysis!$K3*sorted_analysis!$J3 -> 44.99 | M3: 25 | N3: =sorted_analysis!$L3*(sorted_analysis!$M3/100) -> 11.2475 | O3: =sorted_analysis!$L3-sorted_analysis!$N3 -> 33.7425 | P3: 6.5 | Q3: =SUM(sorted_analysis!$O3+sorted_analysis!$P3) -> 40.2425 | R3: =IF(sorted_analysis!$Q3>200,"High Value",IF(sorted_analysis!$Q3>100,"Medium Value","Low Value")) -> Low Value | S3: PayPal | T3: Delivered
A4: ORD-1021 | B4: 45344 | C4: =TEXT(sorted_analysis!$B4,"MMMM") -> February | D4: Joseph Lopez | E4: joseph.l@email.com | F4: North | G4: Detroit | H4: Home & Garden | I4: Wall Clock | J4: 1 | K4: 39.99 | L4: =sorted_analysis!$K4*sorted_analysis!$J4 -> 39.99 | M4: 10 | N4: =sorted_analysis!$L4*(sorted_analysis!$M4/100) -> 3.999 | O4: =sorted_analysis!$L4-sorted_analysis!$N4 -> 35.991 | P4: 5.99 | Q4: =SUM(sorted_analysis!$O4+sorted_analysis!$P4) -> 41.981 | R4: =IF(sorted_analysis!$Q4>200,"High Value",IF(sorted_analysis!$Q4>100,"Medium Value","Low Value")) -> Low Value | S4: Credit Card | T4: Delivered
A5: ORD-1069 | B5: 45465 | C5: =TEXT(sorted_analysis!$B5,"MMMM") -> June | D5: Roger Coleman | E5: roger.c@email.com | F5: North | G5: Detroit | H5: Books | I5: Philosophy | J5: 1 | K5: 44.99 | L5: =sorted_analysis!$K5*sorted_analysis!$J5 -> 44.99 | M5: 0 | N5: =sorted_analysis!$L5*(sorted_analysis!$M5/100) -> 0 | O5: =sorted_analysis!$L5-sorted_analysis!$N5 -> 44.99 | P5: 4.5 | Q5: =SUM(sorted_analysis!$O5+sorted_analysis!$P5) -> 49.49 | R5: =IF(sorted_analysis!$Q5>200,"High Value",IF(sorted_analysis!$Q5>100,"Medium Value","Low Value")) -> Low Value | S5: Credit Card | T5: Delivered
A6: ORD-1073 | B6: 45476 | C6: =TEXT(sorted_analysis!$B6,"MMMM") -> July | D6: Arthur Long | E6: arthur.l@email.com | F6: North | G6: Minneapolis | H6: Books | I6: Poetry | J6: 2 | K6: 24.99 | L6: =sorted_analysis!$K6*sorted_analysis!$J6 -> 49.98 | M6: 0 | N6: =sorted_analysis!$L6*(sorted_analysis!$M6/100) -> 0 | O6: =sorted_analysis!$L6-sorted_analysis!$N6 -> 49.98 | P6: 3.99 | Q6: =SUM(sorted_analysis!$O6+sorted_analysis!$P6) -> 53.97 | R6: =IF(sorted_analysis!$Q6>200,"High Value",IF(sorted_analysis!$Q6>100,"Medium Value","Low Value")) -> Low Value | S6: PayPal | T6: Delivered
A7: ORD-1033 | B7: 45373 | C7: =TEXT(sorted_analysis!$B7,"MMMM") -> March | D7: Jason Phillips | E7: jason.p@email.com | F7: North | G7: Detroit | H7: Books | I7: History Book | J7: 1 | K7: 49.99 | L7: =sorted_analysis!$K7*sorted_analysis!$J7 -> 49.99 | M7: 0 | N7: =sorted_analysis!$L7*(sorted_analysis!$M7/100) -> 0 | O7: =sorted_analysis!$L7-sorted_analysis!$N7 -> 49.99 | P7: 4.99 | Q7: =SUM(sorted_analysis!$O7+sorted_analysis!$P7) -> 54.98 | R7: =IF(sorted_analysis!$Q7>200,"High Value",IF(sorted_analysis!$Q7>100,"Medium Value","Low Value")) -> Low Value | S7: Debit Card | T7: Delivered
A8: ORD-1081 | B8: 45495 | C8: =TEXT(sorted_analysis!$B8,"MMMM") -> July | D8: Russell Gonzales | E8: russell.g@email.com | F8: North | G8: Detroit | H8: Clothing | I8: Gloves | J8: 4 | K8: 14.99 | L8: =sorted_analysis!$K8*sorted_analysis!$J8 -> 59.96 | M8: 10 | N8: =sorted_analysis!$L8*(sorted_analysis!$M8/100) -> 5.996 | O8: =sorted_analysis!$L8-sorted_analysis!$N8 -> 53.964 | P8: 4.5 | Q8: =SUM(sorted_analysis!$O8+sorted_analysis!$P8) -> 58.464 | R8: =IF(sorted_analysis!$Q8>200,"High Value",IF(sorted_analysis!$Q8>100,"Medium Value","Low Value")) -> Low Value | S8: Credit Card | T8: Delivered
A9: ORD-1001 | B9: 45296 | C9: =TEXT(sorted_analysis!$B9,"MMMM") -> January | D9: John Smith | E9: john.smith@email.com | F9: North | G9: New York | H9: Electronics | I9: Wireless Mouse | J9: 2 | K9: 29.99 | L9: =sorted_analysis!$K9*sorted_analysis!$J9 -> 59.98 | M9: 10 | N9: =sorted_analysis!$L9*(sorted_analysis!$M9/100) -> 5.998 | O9: =sorted_analysis!$L9-sorted_analysis!$N9 -> 53.982 | P9: 5.99 | Q9: =SUM(sorted_analysis!$O9+sorted_analysis!$P9) -> 59.972 | R9: =IF(sorted_analysis!$Q9>200,"High Value",IF(sorted_analysis!$Q9>100,"Medium Value","Low Value")) -> Low Value | S9: Credit Card | T9: Delivered
A10: ORD-1061 | B10: 45446 | C10: =TEXT(sorted_analysis!$B10,"MMMM") -> June | D10: Walter Kelly | E10: walter.k@email.com | F10: North | G10: Minneapolis | H10: Home & Garden | I10: Coat Rack | J10: 1 | K10: 69.99 | L10: =sorted_analysis!$K10*sorted_analysis!$J10 -> 69.99 | M10: 15 | N10: =sorted_analysis!$L10*(sorted_analysis!$M10/100) -> 10.4985 | O10: =sorted_analysis!$L10-sorted_analysis!$N10 -> 59.4915 | P10: 8.99 | Q10: =SUM(sorted_analysis!$O10+sorted_analysis!$P10) -> 68.4815 | R10: =IF(sorted_analysis!$Q10>200,"High Value",IF(sorted_analysis!$Q10>100,"Medium Value","Low Value")) -> Low Value | S10: Debit Card | T10: Delivered
A11: ORD-1053 | B11: 45424 | C11: =TEXT(sorted_analysis!$B11,"MMMM") -> May | D11: Jonathan Ward | E11: jonathan.w@email.com | F11: North | G11: Chicago | H11: Electronics | I11: Screen Protector | J11: 5 | K11: 14.99 | L11: =sorted_analysis!$K11*sorted_analysis!$J11 -> 74.95 | M11: 10 | N11: =sorted_analysis!$L11*(sorted_analysis!$M11/100) -> 7.495 | O11: =sorted_analysis!$L11-sorted_analysis!$N11 -> 67.455 | P11: 2.99 | Q11: =SUM(sorted_analysis!$O11+sorted_analysis!$P11) -> 70.445 | R11: =IF(sorted_analysis!$Q11>200,"High Value",IF(sorted_analysis!$Q11>100,"Medium Value","Low Value")) -> Low Value | S11: Credit Card | T11: Processing | Y11: Regions | Z11: Order_Status
A12: ORD-1093 | B12: 45526 | C12: =TEXT(sorted_analysis!$B12,"MMMM") -> August | D12: Henry Wallace | E12: henry.w@email.com | F12: North | G12: Detroit | H12: Home & Garden | I12: Key Holder | J12: 4 | K12: 17.99 | L12: =sorted_analysis!$K12*sorted_analysis!$J12 -> 71.96 | M12: 5 | N12: =sorted_analysis!$L12*(sorted_analysis!$M12/100) -> 3.598 | O12: =sorted_analysis!$L12-sorted_analysis!$N12 -> 68.362 | P12: 4.5 | Q12: =SUM(sorted_analysis!$O12+sorted_analysis!$P12) -> 72.862 | R12: =IF(sorted_analysis!$Q12>200,"High Value",IF(sorted_analysis!$Q12>100,"Medium Value","Low Value")) -> Low Value | S12: Debit Card | T12: Cancelled | Y12: North | Z12: Delivered
A13: ORD-1065 | B13: 45455 | C13: =TEXT(sorted_analysis!$B13,"MMMM") -> June | D13: Gerald Wood | E13: gerald.w@email.com | F13: North | G13: Chicago | H13: Electronics | I13: Cable Organizer | J13: 6 | K13: 12.99 | L13: =sorted_analysis!$K13*sorted_analysis!$J13 -> 77.94 | M13: 5 | N13: =sorted_analysis!$L13*(sorted_analysis!$M13/100) -> 3.897 | O13: =sorted_analysis!$L13-sorted_analysis!$N13 -> 74.043 | P13: 2.99 | Q13: =SUM(sorted_analysis!$O13+sorted_analysis!$P13) -> 77.033 | R13: =IF(sorted_analysis!$Q13>200,"High Value",IF(sorted_analysis!$Q13>100,"Medium Value","Low Value")) -> Low Value | S13: Debit Card | T13: Cancelled | Y13: South | Z13: Processing
A14: ORD-1041 | B14: 45394 | C14: =TEXT(sorted_analysis!$B14,"MMMM") -> April | D14: Eric Rogers | E14: eric.r@email.com | F14: North | G14: Chicago | H14: Electronics | I14: Power Bank | J14: 2 | K14: 44.99 | L14: =sorted_analysis!$K14*sorted_analysis!$J14 -> 89.98 | M14: 15 | N14: =sorted_analysis!$L14*(sorted_analysis!$M14/100) -> 13.497 | O14: =sorted_analysis!$L14-sorted_analysis!$N14 -> 76.483 | P14: 5.5 | Q14: =SUM(sorted_analysis!$O14+sorted_analysis!$P14) -> 81.983 | R14: =IF(sorted_analysis!$Q14>200,"High Value",IF(sorted_analysis!$Q14>100,"Medium Value","Low Value")) -> Low Value | S14: Credit Card | T14: Delivered | Y14: East | Z14: Cancelled
A15: ORD-1097 | B15: 45538 | C15: =TEXT(sorted_analysis!$B15,"MMMM") -> September | D15: Joe Newman | E15: joe.n@email.com | F15: North | G15: Minneapolis | H15: Home & Garden | I15: Mirror | J15: 1 | K15: 89.99 | L15: =sorted_analysis!$K15*sorted_analysis!$J15 -> 89.99 | M15: 20 | N15: =sorted_analysis!$L15*(sorted_analysis!$M15/100) -> 17.998 | O15: =sorted_analysis!$L15-sorted_analysis!$N15 -> 71.992 | P15: 11.99 | Q15: =SUM(sorted_analysis!$O15+sorted_analysis!$P15) -> 83.982 | R15: =IF(sorted_analysis!$Q15>200,"High Value",IF(sorted_analysis!$Q15>100,"Medium Value","Low Value")) -> Low Value | S15: Credit Card | T15: Delivered | Y15: West
A16: ORD-1009 | B16: 45313 | C16: =TEXT(sorted_analysis!$B16,"MMMM") -> January | D16: Robert Thomas | E16: robert.t@email.com | F16: North | G16: Detroit | H16: Electronics | I16: Webcam | J16: 1 | K16: 79.99 | L16: =sorted_analysis!$K16*sorted_analysis!$J16 -> 79.99 | M16: 0 | N16: =sorted_analysis!$L16*(sorted_analysis!$M16/100) -> 0 | O16: =sorted_analysis!$L16-sorted_analysis!$N16 -> 79.99 | P16: 6.5 | Q16: =SUM(sorted_analysis!$O16+sorted_analysis!$P16) -> 86.49 | R16: =IF(sorted_analysis!$Q16>200,"High Value",IF(sorted_analysis!$Q16>100,"Medium Value","Low Value")) -> Low Value | S16: Debit Card | T16: Processing
A17: ORD-1077 | B17: 45485 | C17: =TEXT(sorted_analysis!$B17,"MMMM") -> July | D17: Louis Washington | E17: louis.w@email.com | F17: North | G17: Chicago | H17: Electronics | I17: Car Charger | J17: 5 | K17: 19.99 | L17: =sorted_analysis!$K17*sorted_analysis!$J17 -> 99.95 | M17: 15 | N17: =sorted_analysis!$L17*(sorted_analysis!$M17/100) -> 14.9925 | O17: =sorted_analysis!$L17-sorted_analysis!$N17 -> 84.9575 | P17: 3.99 | Q17: =SUM(sorted_analysis!$O17+sorted_analysis!$P17) -> 88.9475 | R17: =IF(sorted_analysis!$Q17>200,"High Value",IF(sorted_analysis!$Q17>100,"Medium Value","Low Value")) -> Low Value | S17: PayPal | T17: Delivered
A18: ORD-1057 | B18: 45434 | C18: =TEXT(sorted_analysis!$B18,"MMMM") -> May | D18: Dennis Ramirez | E18: dennis.r@email.com | F18: North | G18: Detroit | H18: Home & Garden | I18: Floor Mat | J18: 3 | K18: 29.99 | L18: =sorted_analysis!$K18*sorted_analysis!$J18 -> 89.97 | M18: 5 | N18: =sorted_analysis!$L18*(sorted_analysis!$M18/100) -> 4.4985 | O18: =sorted_analysis!$L18-sorted_analysis!$N18 -> 85.4715 | P18: 5.99 | Q18: =SUM(sorted_analysis!$O18+sorted_analysis!$P18) -> 91.4615 | R18: =IF(sorted_analysis!$Q18>200,"High Value",IF(sorted_analysis!$Q18>100,"Medium Value","Low Value")) -> Low Value | S18: Credit Card | T18: Delivered
A19: ORD-1005 | B19: 45303 | C19: =TEXT(sorted_analysis!$B19,"MMMM") -> January | D19: David Wilson | E19: d.wilson@email.com | F19: North | G19: Chicago | H19: Electronics | I19: Keyboard | J19: 1 | K19: 89.99 | L19: =sorted_analysis!$K19*sorted_analysis!$J19 -> 89.99 | M19: 5 | N19: =sorted_analysis!$L19*(sorted_analysis!$M19/100) -> 4.4995 | O19: =sorted_analysis!$L19-sorted_analysis!$N19 -> 85.4905 | P19: 8.99 | Q19: =SUM(sorted_analysis!$O19+sorted_analysis!$P19) -> 94.4805 | R19: =IF(sorted_analysis!$Q19>200,"High Value",IF(sorted_analysis!$Q19>100,"Medium Value","Low Value")) -> Low Value | S19: Credit Card | T19: Delivered
A20: ORD-1085 | B20: 45507 | C20: =TEXT(sorted_analysis!$B20,"MMMM") -> August | D20: Randy Griffin | E20: randy.g@email.com | F20: North | G20: Minneapolis | H20: Clothing | I20: Socks Pack | J20: 6 | K20: 19.99 | L20: =sorted_analysis!$K20*sorted_analysis!$J20 -> 119.94 | M20: 25 | N20: =sorted_analysis!$L20*(sorted_analysis!$M20/100) -> 29.985 | O20: =sorted_analysis!$L20-sorted_analysis!$N20 -> 89.955 | P20: 4.99 | Q20: =SUM(sorted_analysis!$O20+sorted_analysis!$P20) -> 94.945 | R20: =IF(sorted_analysis!$Q20>200,"High Value",IF(sorted_analysis!$Q20>100,"Medium Value","Low Value")) -> Low Value | S20: Credit Card | T20: Delivered
A21: ORD-1045 | B21: 45404 | C21: =TEXT(sorted_analysis!$B21,"MMMM") -> April | D21: Nicholas Bell | E21: nicholas.b@email.com | F21: North | G21: Detroit | H21: Clothing | I21: Sweatshirt | J21: 2 | K21: 54.99 | L21: =sorted_analysis!$K21*sorted_analysis!$J21 -> 109.98 | M21: 20 | N21: =sorted_analysis!$L21*(sorted_analysis!$M21/100) -> 21.996 | O21: =sorted_analysis!$L21-sorted_analysis!$N21 -> 87.984 | P21: 7.99 | Q21: =SUM(sorted_analysis!$O21+sorted_analysis!$P21) -> 95.974 | R21: =IF(sorted_analysis!$Q21>200,"High Value",IF(sorted_analysis!$Q21>100,"Medium Value","Low Value")) -> Low Value | S21: PayPal | T21: Processing
A22: ORD-1029 | B22: 45363 | C22: =TEXT(sorted_analysis!$B22,"MMMM") -> March | D22: George Mitchell | E22: george.m@email.com | F22: North | G22: Chicago | H22: Electronics | I22: External Hard Drive | J22: 1 | K22: 119.99 | L22: =sorted_analysis!$K22*sorted_analysis!$J22 -> 119.99 | M22: 15 | N22: =sorted_analysis!$L22*(sorted_analysis!$M22/100) -> 17.9985 | O22: =sorted_analysis!$L22-sorted_analysis!$N22 -> 101.9915 | P22: 9.99 | Q22: =SUM(sorted_analysis!$O22+sorted_analysis!$P22) -> 111.9815 | R22: =IF(sorted_analysis!$Q22>200,"High Value",IF(sorted_analysis!$Q22>100,"Medium Value","Low Value")) -> Medium Value | S22: Credit Card | T22: Delivered
A23: ORD-1013 | B23: 45325 | C23: =TEXT(sorted_analysis!$B23,"MMMM") -> February | D23: Christopher Clark | E23: chris.c@email.com | F23: North | G23: Minneapolis | H23: Clothing | I23: Winter Jacket | J23: 1 | K23: 129.99 | L23: =sorted_analysis!$K23*sorted_analysis!$J23 -> 129.99 | M23: 20 | N23: =sorted_analysis!$L23*(sorted_analysis!$M23/100) -> 25.998 | O23: =sorted_analysis!$L23-sorted_analysis!$N23 -> 103.992 | P23: 12.99 | Q23: =SUM(sorted_analysis!$O23+sorted_analysis!$P23) -> 116.982 | R23: =IF(sorted_analysis!$Q23>200,"High Value",IF(sorted_analysis!$Q23>100,"Medium Value","Low Value")) -> Medium Value | S23: Credit Card | T23: Delivered
A24: ORD-1025 | B24: 45354 | C24: =TEXT(sorted_analysis!$B24,"MMMM") -> March | D24: Paul Adams | E24: paul.a@email.com | F24: North | G24: Minneapolis | H24: Home & Garden | I24: Cushion Set | J24: 2 | K24: 54.99 | L24: =sorted_analysis!$K24*sorted_analysis!$J24 -> 109.98 | M24: 0 | N24: =sorted_analysis!$L24*(sorted_analysis!$M24/100) -> 0 | O24: =sorted_analysis!$L24-sorted_analysis!$N24 -> 109.98 | P24: 8.5 | Q24: =SUM(sorted_analysis!$O24+sorted_analysis!$P24) -> 118.48 | R24: =IF(sorted_analysis!$Q24>200,"High Value",IF(sorted_analysis!$Q24>100,"Medium Value","Low Value")) -> Medium Value | S24: Credit Card | T24: Delivered
A25: ORD-1017 | B25: 45334 | C25: =TEXT(sorted_analysis!$B25,"MMMM") -> February | D25: Matthew Allen | E25: matt.a@email.com | F25: North | G25: Chicago | H25: Electronics | I25: Monitor | J25: 1 | K25: 299.99 | L25: =sorted_analysis!$K25*sorted_analysis!$J25 -> 299.99 | M25: 10 | N25: =sorted_analysis!$L25*(sorted_analysis!$M25/100) -> 29.999 | O25: =sorted_analysis!$L25-sorted_analysis!$N25 -> 269.991 | P25: 15.99 | Q25: =SUM(sorted_analysis!$O25+sorted_analysis!$P25) -> 285.981 | R25: =IF(sorted_analysis!$Q25>200,"High Value",IF(sorted_analysis!$Q25>100,"Medium Value","Low Value")) -> High Value | S25: Credit Card | T25: Delivered
A26: ORD-1089 | B26: 45516 | C26: =TEXT(sorted_analysis!$B26,"MMMM") -> August | D26: Jack Ford | E26: jack.f@email.com | F26: North | G26: Chicago | H26: Electronics | I26: VR Headset | J26: 1 | K26: 399.99 | L26: =sorted_analysis!$K26*sorted_analysis!$J26 -> 399.99 | M26: 20 | N26: =sorted_analysis!$L26*(sorted_analysis!$M26/100) -> 79.998 | O26: =sorted_analysis!$L26-sorted_analysis!$N26 -> 319.992 | P26: 19.99 | Q26: =SUM(sorted_analysis!$O26+sorted_analysis!$P26) -> 339.982 | R26: =IF(sorted_analysis!$Q26>200,"High Value",IF(sorted_analysis!$Q26>100,"Medium Value","Low Value")) -> High Value | S26: Debit Card | T26: Delivered
F27: North Count | Q27: =SUBTOTAL(3,Q2:Q26) -> 25
F28: North Total | Q28: =SUBTOTAL(9,Q2:Q26) -> 2376.8215
F29: North Average | Q29: =SUBTOTAL(1,Q2:Q26) -> 95.07286
A30: ORD-1066 | B30: 45458 | C30: =TEXT(sorted_analysis!$B30,"MMMM") -> June | D30: Judith Barnes | E30: judith.b@email.com | F30: South | G30: Miami | H30: Home & Garden | I30: Napkin Holder | J30: 2 | K30: 24.99 | L30: =sorted_analysis!$K30*sorted_analysis!$J30 -> 49.98 | M30: 15 | N30: =sorted_analysis!$L30*(sorted_analysis!$M30/100) -> 7.497 | O30: =sorted_analysis!$L30-sorted_analysis!$N30 -> 42.483 | P30: 5.5 | Q30: =SUM(sorted_analysis!$O30+sorted_analysis!$P30) -> 47.983 | R30: =IF(sorted_analysis!$Q30>200,"High Value",IF(sorted_analysis!$Q30>100,"Medium Value","Low Value")) -> Low Value | S30: PayPal | T30: Delivered
A31: ORD-1042 | B31: 45397 | C31: =TEXT(sorted_analysis!$B31,"MMMM") -> April | D31: Rebecca Reed | E31: rebecca.r@email.com | F31: South | G31: Atlanta | H31: Books | I31: Biography | J31: 1 | K31: 44.99 | L31: =sorted_analysis!$K31*sorted_analysis!$J31 -> 44.99 | M31: 0 | N31: =sorted_analysis!$L31*(sorted_analysis!$M31/100) -> 0 | O31: =sorted_analysis!$L31-sorted_analysis!$N31 -> 44.99 | P31: 4.5 | Q31: =SUM(sorted_analysis!$O31+sorted_analysis!$P31) -> 49.49 | R31: =IF(sorted_analysis!$Q31>200,"High Value",IF(sorted_analysis!$Q31>100,"Medium Value","Low Value")) -> Low Value | S31: PayPal | T31: Delivered
A32: ORD-1062 | B32: 45448 | C32: =TEXT(sorted_analysis!$B32,"MMMM") -> June | D32: Teresa Sanders | E32: teresa.s@email.com | F32: South | G32: Dallas | H32: Electronics | I32: Phone Holder | J32: 3 | K32: 19.99 | L32: =sorted_analysis!$K32*sorted_analysis!$J32 -> 59.97 | M32: 20 | N32: =sorted_analysis!$L32*(sorted_analysis!$M32/100) -> 11.994 | O32: =sorted_analysis!$L32-sorted_analysis!$N32 -> 47.976 | P32: 4.5 | Q32: =SUM(sorted_analysis!$O32+sorted_analysis!$P32) -> 52.476 | R32: =IF(sorted_analysis!$Q32>200,"High Value",IF(sorted_analysis!$Q32>100,"Medium Value","Low Value")) -> Low Value | S32: Credit Card | T32: Delivered
A33: ORD-1002 | B33: 45298 | C33: =TEXT(sorted_analysis!$B33,"MMMM") -> January | D33: Sarah Johnson | E33: sarah.j@email.com | F33: South | G33: Miami | H33: Home & Garden | I33: Plant Pot Set | J33: 1 | K33: 45.5 | L33: =sorted_analysis!$K33*sorted_analysis!$J33 -> 45.5 | M33: 0 | N33: =sorted_analysis!$L33*(sorted_analysis!$M33/100) -> 0 | O33: =sorted_analysis!$L33-sorted_analysis!$N33 -> 45.5 | P33: 7.5 | Q33: =SUM(sorted_analysis!$O33+sorted_analysis!$P33) -> 53 | R33: =IF(sorted_analysis!$Q33>200,"High Value",IF(sorted_analysis!$Q33>100,"Medium Value","Low Value")) -> Low Value | S33: PayPal | T33: Delivered
A34: ORD-1078 | B34: 45488 | C34: =TEXT(sorted_analysis!$B34,"MMMM") -> July | D34: Evelyn Butler | E34: evelyn.b@email.com | F34: South | G34: Dallas | H34: Books | I34: Memoir | J34: 1 | K34: 49.99 | L34: =sorted_analysis!$K34*sorted_analysis!$J34 -> 49.99 | M34: 0 | N34: =sorted_analysis!$L34*(sorted_analysis!$M34/100) -> 0 | O34: =sorted_analysis!$L34-sorted_analysis!$N34 -> 49.99 | P34: 4.99 | Q34: =SUM(sorted_analysis!$O34+sorted_analysis!$P34) -> 54.98 | R34: =IF(sorted_analysis!$Q34>200,"High Value",IF(sorted_analysis!$Q34>100,"Medium Value","Low Value")) -> Low Value | S34: Credit Card | T34: Delivered
A35: ORD-1046 | B35: 45407 | C35: =TEXT(sorted_analysis!$B35,"MMMM") -> April | D35: Deborah Murphy | E35: deborah.m@email.com | F35: South | G35: Dallas | H35: Books | I35: Travel Guide | J35: 2 | K35: 29.99 | L35: =sorted_analysis!$K35*sorted_analysis!$J35 -> 59.98 | M35: 15 | N35: =sorted_analysis!$L35*(sorted_analysis!$M35/100) -> 8.997 | O35: =sorted_analysis!$L35-sorted_analysis!$N35 -> 50.983 | P35: 4.99 | Q35: =SUM(sorted_analysis!$O35+sorted_analysis!$P35) -> 55.973 | R35: =IF(sorted_analysis!$Q35>200,"High Value",IF(sorted_analysis!$Q35>100,"Medium Value","Low Value")) -> Low Value | S35: Credit Card | T35: Delivered
A36: ORD-1074 | B36: 45478 | C36: =TEXT(sorted_analysis!$B36,"MMMM") -> July | D36: Frances Patterson | E36: frances.p@email.com | F36: South | G36: Atlanta | H36: Electronics | I36: Ring Light | J36: 1 | K36: 59.99 | L36: =sorted_analysis!$K36*sorted_analysis!$J36 -> 59.99 | M36: 20 | N36: =sorted_analysis!$L36*(sorted_analysis!$M36/100) -> 11.998 | O36: =sorted_analysis!$L36-sorted_analysis!$N36 -> 47.992 | P36: 7.99 | Q36: =SUM(sorted_analysis!$O36+sorted_analysis!$P36) -> 55.982 | R36: =IF(sorted_analysis!$Q36>200,"High Value",IF(sorted_analysis!$Q36>100,"Medium Value","Low Value")) -> Low Value | S36: Credit Card | T36: Processing
A37: ORD-1054 | B37: 45427 | C37: =TEXT(sorted_analysis!$B37,"MMMM") -> May | D37: Barbara Torres | E37: barbara.t@email.com | F37: South | G37: Houston | H37: Clothing | I37: Formal Shirt | J37: 1 | K37: 64.99 | L37: =sorted_analysis!$K37*sorted_analysis!$J37 -> 64.99 | M37: 20 | N37: =sorted_analysis!$L37*(sorted_analysis!$M37/100) -> 12.998 | O37: =sorted_analysis!$L37-sorted_analysis!$N37 -> 51.992 | P37: 7.99 | Q37: =SUM(sorted_analysis!$O37+sorted_analysis!$P37) -> 59.982 | R37: =IF(sorted_analysis!$Q37>200,"High Value",IF(sorted_analysis!$Q37>100,"Medium Value","Low Value")) -> Low Value | S37: Debit Card | T37: Delivered
A38: ORD-1082 | B38: 45498 | C38: =TEXT(sorted_analysis!$B38,"MMMM") -> July | D38: Cheryl Bryant | E38: cheryl.b@email.com | F38: South | G38: Miami | H38: Books | I38: Graphic Novel | J38: 2 | K38: 34.99 | L38: =sorted_analysis!$K38*sorted_analysis!$J38 -> 69.98 | M38: 15 | N38: =sorted_analysis!$L38*(sorted_analysis!$M38/100) -> 10.497 | O38: =sorted_analysis!$L38-sorted_analysis!$N38 -> 59.483 | P38: 4.5 | Q38: =SUM(sorted_analysis!$O38+sorted_analysis!$P38) -> 63.983 | R38: =IF(sorted_analysis!$Q38>200,"High Value",IF(sorted_analysis!$Q38>100,"Medium Value","Low Value")) -> Low Value | S38: Debit Card | T38: Processing
A39: ORD-1090 | B39: 45519 | C39: =TEXT(sorted_analysis!$B39,"MMMM") -> August | D39: Ann Hamilton | E39: ann.h@email.com | F39: South | G39: Atlanta | H39: Clothing | I39: Wallet | J39: 2 | K39: 34.99 | L39: =sorted_analysis!$K39*sorted_analysis!$J39 -> 69.98 | M39: 10 | N39: =sorted_analysis!$L39*(sorted_analysis!$M39/100) -> 6.998 | O39: =sorted_analysis!$L39-sorted_analysis!$N39 -> 62.982 | P39: 5.99 | Q39: =SUM(sorted_analysis!$O39+sorted_analysis!$P39) -> 68.972 | R39: =IF(sorted_analysis!$Q39>200,"High Value",IF(sorted_analysis!$Q39>100,"Medium Value","Low Value")) -> Low Value | S39: Credit Card | T39: Delivered
A40: ORD-1094 | B40: 45529 | C40: =TEXT(sorted_analysis!$B40,"MMMM") -> August | D40: Diana Woods | E40: diana.w@email.com | F40: South | G40: Dallas | H40: Clothing | I40: Sunglasses | J40: 2 | K40: 44.99 | L40: =sorted_analysis!$K40*sorted_analysis!$J40 -> 89.98 | M40: 25 | N40: =sorted_analysis!$L40*(sorted_analysis!$M40/100) -> 22.495 | O40: =sorted_analysis!$L40-sorted_analysis!$N40 -> 67.485 | P40: 6.5 | Q40: =SUM(sorted_analysis!$O40+sorted_analysis!$P40) -> 73.985 | R40: =IF(sorted_analysis!$Q40>200,"High Value",IF(sorted_analysis!$Q40>100,"Medium Value","Low Value")) -> Low Value | S40: PayPal | T40: Delivered
A41: ORD-1026 | B41: 45356 | C41: =TEXT(sorted_analysis!$B41,"MMMM") -> March | D41: Carol Baker | E41: carol.b@email.com | F41: South | G41: Atlanta | H41: Electronics | I41: Phone Case | J41: 4 | K41: 19.99 | L41: =sorted_analysis!$K41*sorted_analysis!$J41 -> 79.96 | M41: 10 | N41: =sorted_analysis!$L41*(sorted_analysis!$M41/100) -> 7.996 | O41: =sorted_analysis!$L41-sorted_analysis!$N41 -> 71.964 | P41: 3.99 | Q41: =SUM(sorted_analysis!$O41+sorted_analysis!$P41) -> 75.954 | R41: =IF(sorted_analysis!$Q41>200,"High Value",IF(sorted_analysis!$Q41>100,"Medium Value","Low Value")) -> Low Value | S41: Debit Card | T41: Delivered
... A54: ORD-1098 | B54: 45540 | C54: =TEXT(sorted_analysis!$B54,"MMMM") -> September | D54: Frances Hunter | E54: frances.h@email.com | F54: South | G54: Miami | H54: Electronics | I54: Action Camera | J54: 1 | K54: 249.99 | L54: =sorted_analysis!$K54*sorted_analysis!$J54 -> 249.99 | M54: 15 | N54: =sorted_analysis!$L54*(sorted_analysis!$M54/100) -> 37.4985 | O54: =sorted_analysis!$L54-sorted_analysis!$N54 -> 212.4915 | P54: 14.99 | Q54: =SUM(sorted_analysis!$O54+sorted_analysis!$P54) -> 227.4815 | R54: =IF(sorted_analysis!$Q54>200,"High Value",IF(sorted_analysis!$Q54>100,"Medium Value","Low Value")) -> High Value | S54: PayPal | T54: Delivered
F55: South Count | Q55: =SUBTOTAL(3,Q30:Q54) -> 25
F56: South Total | Q56: =SUBTOTAL(9,Q30:Q54) -> 2124.166
F57: South Average | Q57: =SUBTOTAL(1,Q30:Q54) -> 84.96664
A58: ORD-1087 | B58: 45512 | C58: =TEXT(sorted_analysis!$B58,"MMMM") -> August | D58: Philip Hayes | E58: philip.h@email.com | F58: East | G58: Boston | H58: Books | I58: Romance | J58: 1 | K58: 29.99 | L58: =sorted_analysis!$K58*sorted_analysis!$J58 -> 29.99 | M58: 0 | N58: =sorted_analysis!$L58*(sorted_analysis!$M58/100) -> 0 | O58: =sorted_analysis!$L58-sorted_analysis!$N58 -> 29.99 | P58: 3.99 | Q58: =SUM(sorted_analysis!$O58+sorted_analysis!$P58) -> 33.98 | R58: =IF(sorted_analysis!$Q58>200,"High Value",IF(sorted_analysis!$Q58>100,"Medium Value","Low Value")) -> Low Value | S58: PayPal | T58: Delivered
A59: ORD-1047 | B59: 45410 | C59: =TEXT(sorted_analysis!$B59,"MMMM") -> April | D59: Scott Bailey | E59: scott.b@email.com | F59: East | G59: New York | H59: Electronics | I59: USB Hub | J59: 1 | K59: 34.99 | L59: =sorted_analysis!$K59*sorted_analysis!$J59 -> 34.99 | M59: 0 | N59: =sorted_analysis!$L59*(sorted_analysis!$M59/100) -> 0 | O59: =sorted_analysis!$L59-sorted_analysis!$N59 -> 34.99 | P59: 4.5 | Q59: =SUM(sorted_analysis!$O59+sorted_analysis!$P59) -> 39.49 | R59: =IF(sorted_analysis!$Q59>200,"High Value",IF(sorted_analysis!$Q59>100,"Medium Value","Low Value")) -> Low Value | S59: Debit Card | T59: Delivered
A60: ORD-1051 | B60: 45420 | C60: =TEXT(sorted_analysis!$B60,"MMMM") -> May | D60: Frank Cox | E60: frank.c@email.com | F60: East | G60: Boston | H60: Books | I60: Science Fiction | J60: 1 | K60: 39.99 | L60: =sorted_analysis!$K60*sorted_analysis!$J60 -> 39.99 | M60: 0 | N60: =sorted_analysis!$L60*(sorted_analysis!$M60/100) -> 0 | O60: =sorted_analysis!$L60-sorted_analysis!$N60 -> 39.99 | P60: 3.99 | Q60: =SUM(sorted_analysis!$O60+sorted_analysis!$P60) -> 43.98 | R60: =IF(sorted_analysis!$Q60>200,"High Value",IF(sorted_analysis!$Q60>100,"Medium Value","Low Value")) -> Low Value | S60: Debit Card | T60: Delivered
A61: ORD-1091 | B61: 45522 | C61: =TEXT(sorted_analysis!$B61,"MMMM") -> August | D61: Carl Graham | E61: carl.g@email.com | F61: East | G61: Philadelphia | H61: Books | I61: Horror | J61: 1 | K61: 39.99 | L61: =sorted_analysis!$K61*sorted_analysis!$J61 -> 39.99 | M61: 0 | N61: =sorted_analysis!$L61*(sorted_analysis!$M61/100) -> 0 | O61: =sorted_analysis!$L61-sorted_analysis!$N61 -> 39.99 | P61: 4.5 | Q61: =SUM(sorted_analysis!$O61+sorted_analysis!$P61) -> 44.49 | R61: =IF(sorted_analysis!$Q61>200,"High Value",IF(sorted_analysis!$Q61>100,"Medium Value","Low Value")) -> Low Value | S61: PayPal | T61: Delivered
A62: ORD-1019 | B62: 45340 | C62: =TEXT(sorted_analysis!$B62,"MMMM") -> February | D62: Steven King | E62: steven.k@email.com | F62: East | G62: Philadelphia | H62: Books | I62: Marketing 101 | J62: 1 | K62: 42.99 | L62: =sorted_analysis!$K62*sorted_analysis!$J62 -> 42.99 | M62: 0 | N62: =sorted_analysis!$L62*(sorted_analysis!$M62/100) -> 0 | O62: =sorted_analysis!$L62-sorted_analysis!$N62 -> 42.99 | P62: 3.99 | Q62: =SUM(sorted_analysis!$O62+sorted_analysis!$P62) -> 46.98 | R62: =IF(sorted_analysis!$Q62>200,"High Value",IF(sorted_analysis!$Q62>100,"Medium Value","Low Value")) -> Low Value | S62: Credit Card | T62: Delivered
A63: ORD-1007 | B63: 45309 | C63: =TEXT(sorted_analysis!$B63,"MMMM") -> January | D63: James Martinez | E63: james.m@email.com | F63: East | G63: Philadelphia | H63: Books | I63: Programming Guide | J63: 1 | K63: 54.99 | L63: =sorted_analysis!$K63*sorted_analysis!$J63 -> 54.99 | M63: 10 | N63: =sorted_analysis!$L63*(sorted_analysis!$M63/100) -> 5.499 | O63: =sorted_analysis!$L63-sorted_analysis!$N63 -> 49.491 | P63: 3.99 | Q63: =SUM(sorted_analysis!$O63+sorted_analysis!$P63) -> 53.481 | R63: =IF(sorted_analysis!$Q63>200,"High Value",IF(sorted_analysis!$Q63>100,"Medium Value","Low Value")) -> Low Value | S63: Credit Card | T63: Cancelled
A64: ORD-1011 | B64: 45319 | C64: =TEXT(sorted_analysis!$B64,"MMMM") -> January | D64: William White | E64: william.w@email.com | F64: East | G64: New York | H64: Electronics | I64: Laptop Stand | J64: 1 | K64: 49.99 | L64: =sorted_analysis!$K64*sorted_analysis!$J64 -> 49.99 | M64: 10 | N64: =sorted_analysis!$L64*(sorted_analysis!$M64/100) -> 4.999 | O64: =sorted_analysis!$L64-sorted_analysis!$N64 -> 44.991 | P64: 8.5 | Q64: =SUM(sorted_analysis!$O64+sorted_analysis!$P64) -> 53.491 | R64: =IF(sorted_analysis!$Q64>200,"High Value",IF(sorted_analysis!$Q64>100,"Medium Value","Low Value")) -> Low Value | S64: Credit Card | T64: Delivered
A65: ORD-1003 | B65: 45299 | C65: =TEXT(sorted_analysis!$B65,"MMMM") -> January | D65: Michael Brown | E65: m.brown@email.com | F65: East | G65: Boston | H65: Electronics | I65: USB Cable | J65: 5 | K65: 12.99 | L65: =sorted_analysis!$K65*sorted_analysis!$J65 -> 64.95 | M65: 15 | N65: =sorted_analysis!$L65*(sorted_analysis!$M65/100) -> 9.7425 | O65: =sorted_analysis!$L65-sorted_analysis!$N65 -> 55.2075 | P65: 4.99 | Q65: =SUM(sorted_analysis!$O65+sorted_analysis!$P65) -> 60.1975 | R65: =IF(sorted_analysis!$Q65>200,"High Value",IF(sorted_analysis!$Q65>100,"Medium Value","Low Value")) -> Low Value | S65: Credit Card | T65: Delivered
A66: ORD-1015 | B66: 45330 | C66: =TEXT(sorted_analysis!$B66,"MMMM") -> February | D66: Daniel Walker | E66: daniel.w@email.com | F66: East | G66: Boston | H66: Books | I66: Data Science | J66: 1 | K66: 64.99 | L66: =sorted_analysis!$K66*sorted_analysis!$J66 -> 64.99 | M66: 15 | N66: =sorted_analysis!$L66*(sorted_analysis!$M66/100) -> 9.7485 | O66: =sorted_analysis!$L66-sorted_analysis!$N66 -> 55.2415 | P66: 4.99 | Q66: =SUM(sorted_analysis!$O66+sorted_analysis!$P66) -> 60.2315 | R66: =IF(sorted_analysis!$Q66>200,"High Value",IF(sorted_analysis!$Q66>100,"Medium Value","Low Value")) -> Low Value | S66: Credit Card | T66: Delivered
A67: ORD-1079 | B67: 45491 | C67: =TEXT(sorted_analysis!$B67,"MMMM") -> July | D67: Eugene Simmons | E67: eugene.s@email.com | F67: East | G67: Philadelphia | H67: Home & Garden | I67: Cutting Board | J67: 2 | K67: 29.99 | L67: =sorted_analysis!$K67*sorted_analysis!$J67 -> 59.98 | M67: 5 | N67: =sorted_analysis!$L67*(sorted_analysis!$M67/100) -> 2.999 | O67: =sorted_analysis!$L67-sorted_analysis!$N67 -> 56.981 | P67: 5.99 | Q67: =SUM(sorted_analysis!$O67+sorted_analysis!$P67) -> 62.971 | R67: =IF(sorted_analysis!$Q67>200,"High Value",IF(sorted_analysis!$Q67>100,"Medium Value","Low Value")) -> Low Value | S67: Debit Card | T67: Cancelled
A68: ORD-1035 | B68: 45379 | C68: =TEXT(sorted_analysis!$B68,"MMMM") -> March | D68: Ryan Parker | E68: ryan.p@email.com | F68: East | G68: New York | H68: Electronics | I68: Gaming Mouse | J68: 1 | K68: 69.99 | L68: =sorted_analysis!$K68*sorted_analysis!$J68 -> 69.99 | M68: 10 | N68: =sorted_analysis!$L68*(sorted_analysis!$M68/100) -> 6.999 | O68: =sorted_analysis!$L68-sorted_analysis!$N68 -> 62.991 | P68: 6.5 | Q68: =SUM(sorted_analysis!$O68+sorted_analysis!$P68) -> 69.491 | R68: =IF(sorted_analysis!$Q68>200,"High Value",IF(sorted_analysis!$Q68>100,"Medium Value","Low Value")) -> Low Value | S68: PayPal | T68: Cancelled
A69: ORD-1075 | B69: 45481 | C69: =TEXT(sorted_analysis!$B69,"MMMM") -> July | D69: Roy Hughes | E69: roy.h@email.com | F69: East | G69: Boston | H69: Home & Garden | I69: Trash Can | J69: 2 | K69: 34.99 | L69: =sorted_analysis!$K69*sorted_analysis!$J69 -> 69.98 | M69: 10 | N69: =sorted_analysis!$L69*(sorted_analysis!$M69/100) -> 6.998 | O69: =sorted_analysis!$L69-sorted_analysis!$N69 -> 62.982 | P69: 6.99 | Q69: =SUM(sorted_analysis!$O69+sorted_analysis!$P69) -> 69.972 | R69: =IF(sorted_analysis!$Q69>200,"High Value",IF(sorted_analysis!$Q69>100,"Medium Value","Low Value")) -> Low Value | S69: Debit Card | T69: Delivered
... A82: ORD-1095 | B82: 45532 | C82: =TEXT(sorted_analysis!$B82,"MMMM") -> August | D82: Peter West | E82: peter.w@email.com | F82: East | G82: New York | H82: Electronics | I82: Drone | J82: 1 | K82: 499.99 | L82: =sorted_analysis!$K82*sorted_analysis!$J82 -> 499.99 | M82: 10 | N82: =sorted_analysis!$L82*(sorted_analysis!$M82/100) -> 49.999 | O82: =sorted_analysis!$L82-sorted_analysis!$N82 -> 449.991 | P82: 24.99 | Q82: =SUM(sorted_analysis!$O82+sorted_analysis!$P82) -> 474.981 | R82: =IF(sorted_analysis!$Q82>200,"High Value",IF(sorted_analysis!$Q82>100,"Medium Value","Low Value")) -> High Value | S82: Credit Card | T82: Processing
F83: East Count | Q83: =SUBTOTAL(3,Q58:Q82) -> 25
F84: East Total | Q84: =SUBTOTAL(9,Q58:Q82) -> 2262.1475
F85: East Average | Q85: =SUBTOTAL(1,Q58:Q82) -> 90.4859
A86: ORD-1028 | B86: 45361 | C86: =TEXT(sorted_analysis!$B86,"MMMM") -> March | D86: Ruth Carter | E86: ruth.c@email.com | F86: West | G86: Seattle | H86: Books | I86: Fiction Novel | J86: 1 | K86: 24.99 | L86: =sorted_analysis!$K86*sorted_analysis!$J86 -> 24.99 | M86: 0 | N86: =sorted_analysis!$L86*(sorted_analysis!$M86/100) -> 0 | O86: =sorted_analysis!$L86-sorted_analysis!$N86 -> 24.99 | P86: 3.5 | Q86: =SUM(sorted_analysis!$O86+sorted_analysis!$P86) -> 28.49 | R86: =IF(sorted_analysis!$Q86>200,"High Value",IF(sorted_analysis!$Q86>100,"Medium Value","Low Value")) -> Low Value | S86: PayPal | T86: Delivered
A87: ORD-1044 | B87: 45402 | C87: =TEXT(sorted_analysis!$B87,"MMMM") -> April | D87: Virginia Morgan | E87: virginia.m@email.com | F87: West | G87: San Diego | H87: Electronics | I87: Wireless Charger | J87: 1 | K87: 39.99 | L87: =sorted_analysis!$K87*sorted_analysis!$J87 -> 39.99 | M87: 10 | N87: =sorted_analysis!$L87*(sorted_analysis!$M87/100) -> 3.999 | O87: =sorted_analysis!$L87-sorted_analysis!$N87 -> 35.991 | P87: 5.99 | Q87: =SUM(sorted_analysis!$O87+sorted_analysis!$P87) -> 41.981 | R87: =IF(sorted_analysis!$Q87>200,"High Value",IF(sorted_analysis!$Q87>100,"Medium Value","Low Value")) -> Low Value | S87: Debit Card | T87: Delivered
A88: ORD-1072 | B88: 45474 | C88: =TEXT(sorted_analysis!$B88,"MMMM") -> July | D88: Julia Powell | E88: julia.p@email.com | F88: West | G88: San Francisco | H88: Clothing | I88: Leather Belt | J88: 1 | K88: 39.99 | L88: =sorted_analysis!$K88*sorted_analysis!$J88 -> 39.99 | M88: 5 | N88: =sorted_analysis!$L88*(sorted_analysis!$M88/100) -> 1.9995 | O88: =sorted_analysis!$L88-sorted_analysis!$N88 -> 37.9905 | P88: 6.5 | Q88: =SUM(sorted_analysis!$O88+sorted_analysis!$P88) -> 44.4905 | R88: =IF(sorted_analysis!$Q88>200,"High Value",IF(sorted_analysis!$Q88>100,"Medium Value","Low Value")) -> Low Value | S88: Debit Card | T88: Delivered
A89: ORD-1076 | B89: 45483 | C89: =TEXT(sorted_analysis!$B89,"MMMM") -> July | D89: Janice Flores | E89: janice.f@email.com | F89: West | G89: Portland | H89: Clothing | I89: Beach Hat | J89: 3 | K89: 19.99 | L89: =sorted_analysis!$K89*sorted_analysis!$J89 -> 59.97 | M89: 25 | N89: =sorted_analysis!$L89*(sorted_analysis!$M89/100) -> 14.9925 | O89: =sorted_analysis!$L89-sorted_analysis!$N89 -> 44.9775 | P89: 5.5 | Q89: =SUM(sorted_analysis!$O89+sorted_analysis!$P89) -> 50.4775 | R89: =IF(sorted_analysis!$Q89>200,"High Value",IF(sorted_analysis!$Q89>100,"Medium Value","Low Value")) -> Low Value | S89: Credit Card | T89: Delivered
A90: ORD-1020 | B90: 45342 | C90: =TEXT(sorted_analysis!$B90,"MMMM") -> February | D90: Betty Wright | E90: betty.w@email.com | F90: West | G90: San Diego | H90: Electronics | I90: Mouse Pad | J90: 6 | K90: 9.99 | L90: =sorted_analysis!$K90*sorted_analysis!$J90 -> 59.94 | M90: 15 | N90: =sorted_analysis!$L90*(sorted_analysis!$M90/100) -> 8.991 | O90: =sorted_analysis!$L90-sorted_analysis!$N90 -> 50.949 | P90: 2.99 | Q90: =SUM(sorted_analysis!$O90+sorted_analysis!$P90) -> 53.939 | R90: =IF(sorted_analysis!$Q90>200,"High Value",IF(sorted_analysis!$Q90>100,"Medium Value","Low Value")) -> Low Value | S90: PayPal | T90: Cancelled
A91: ORD-1004 | B91: 45301 | C91: =TEXT(sorted_analysis!$B91,"MMMM") -> January | D91: Emily Davis | E91: emily.d@email.com | F91: West | G91: Los Angeles | H91: Clothing | I91: Cotton T-Shirt | J91: 3 | K91: 19.99 | L91: =sorted_analysis!$K91*sorted_analysis!$J91 -> 59.97 | M91: 20 | N91: =sorted_analysis!$L91*(sorted_analysis!$M91/100) -> 11.994 | O91: =sorted_analysis!$L91-sorted_analysis!$N91 -> 47.976 | P91: 6.5 | Q91: =SUM(sorted_analysis!$O91+sorted_analysis!$P91) -> 54.476 | R91: =IF(sorted_analysis!$Q91>200,"High Value",IF(sorted_analysis!$Q91>100,"Medium Value","Low Value")) -> Low Value | S91: Debit Card | T91: Delivered
A92: ORD-1064 | B92: 45453 | C92: =TEXT(sorted_analysis!$B92,"MMMM") -> June | D92: Gloria Bennett | E92: gloria.b@email.com | F92: West | G92: San Diego | H92: Books | I92: Psychology | J92: 1 | K92: 54.99 | L92: =sorted_analysis!$K92*sorted_analysis!$J92 -> 54.99 | M92: 10 | N92: =sorted_analysis!$L92*(sorted_analysis!$M92/100) -> 5.499 | O92: =sorted_analysis!$L92-sorted_analysis!$N92 -> 49.491 | P92: 4.99 | Q92: =SUM(sorted_analysis!$O92+sorted_analysis!$P92) -> 54.481 | R92: =IF(sorted_analysis!$Q92>200,"High Value",IF(sorted_analysis!$Q92>100,"Medium Value","Low Value")) -> Low Value | S92: Credit Card | T92: Delivered
A93: ORD-1096 | B93: 45536 | C93: =TEXT(sorted_analysis!$B93,"MMMM") -> September | D93: Alice Cole | E93: alice.c@email.com | F93: West | G93: Portland | H93: Books | I93: Children's Book | J93: 3 | K93: 19.99 | L93: =sorted_analysis!$K93*sorted_analysis!$J93 -> 59.97 | M93: 0 | N93: =sorted_analysis!$L93*(sorted_analysis!$M93/100) -> 0 | O93: =sorted_analysis!$L93-sorted_analysis!$N93 -> 59.97 | P93: 4.99 | Q93: =SUM(sorted_analysis!$O93+sorted_analysis!$P93) -> 64.96 | R93: =IF(sorted_analysis!$Q93>200,"High Value",IF(sorted_analysis!$Q93>100,"Medium Value","Low Value")) -> Low Value | S93: Debit Card | T93: Delivered
A94: ORD-1060 | B94: 45444 | C94: =TEXT(sorted_analysis!$B94,"MMMM") -> June | D94: Janet Brooks | E94: janet.b@email.com | F94: West | G94: Los Angeles | H94: Books | I94: Art Book | J94: 1 | K94: 59.99 | L94: =sorted_analysis!$K94*sorted_analysis!$J94 -> 59.99 | M94: 0 | N94: =sorted_analysis!$L94*(sorted_analysis!$M94/100) -> 0 | O94: =sorted_analysis!$L94-sorted_analysis!$N94 -> 59.99 | P94: 5.99 | Q94: =SUM(sorted_analysis!$O94+sorted_analysis!$P94) -> 65.98 | R94: =IF(sorted_analysis!$Q94>200,"High Value",IF(sorted_analysis!$Q94>100,"Medium Value","Low Value")) -> Low Value | S94: Credit Card | T94: Delivered
A95: ORD-1040 | B95: 45392 | C95: =TEXT(sorted_analysis!$B95,"MMMM") -> April | D95: Stephanie Morris | E95: stephanie.m@email.com | F95: West | G95: Los Angeles | H95: Clothing | I95: Yoga Pants | J95: 2 | K95: 39.99 | L95: =sorted_analysis!$K95*sorted_analysis!$J95 -> 79.98 | M95: 20 | N95: =sorted_analysis!$L95*(sorted_analysis!$M95/100) -> 15.996 | O95: =sorted_analysis!$L95-sorted_analysis!$N95 -> 63.984 | P95: 6.99 | Q95: =SUM(sorted_analysis!$O95+sorted_analysis!$P95) -> 70.974 | R95: =IF(sorted_analysis!$Q95>200,"High Value",IF(sorted_analysis!$Q95>100,"Medium Value","Low Value")) -> Low Value | S95: Debit Card | T95: Delivered
A96: ORD-1012 | B96: 45323 | C96: =TEXT(sorted_analysis!$B96,"MMMM") -> February | D96: Mary Harris | E96: mary.h@email.com | F96: West | G96: Seattle | H96: Home & Garden | I96: Decorative Vase | J96: 3 | K96: 24.99 | L96: =sorted_analysis!$K96*sorted_analysis!$J96 -> 74.97 | M96: 0 | N96: =sorted_analysis!$L96*(sorted_analysis!$M96/100) -> 0 | O96: =sorted_analysis!$L96-sorted_analysis!$N96 -> 74.97 | P96: 5.99 | Q96: =SUM(sorted_analysis!$O96+sorted_analysis!$P96) -> 80.96 | R96: =IF(sorted_analysis!$Q96>200,"High Value",IF(sorted_analysis!$Q96>100,"Medium Value","Low Value")) -> Low Value | S96: PayPal | T96: Delivered
A97: ORD-1068 | B97: 45463 | C97: =TEXT(sorted_analysis!$B97,"MMMM") -> June | D97: Rose Henderson | E97: rose.h@email.com | F97: West | G97: Seattle | H97: Electronics | I97: Laptop Bag | J97: 1 | K97: 89.99 | L97: =sorted_analysis!$K97*sorted_analysis!$J97 -> 89.99 | M97: 20 | N97: =sorted_analysis!$L97*(sorted_analysis!$M97/100) -> 17.998 | O97: =sorted_analysis!$L97-sorted_analysis!$N97 -> 71.992 | P97: 9.99 | Q97: =SUM(sorted_analysis!$O97+sorted_analysis!$P97) -> 81.982 | R97: =IF(sorted_analysis!$Q97>200,"High Value",IF(sorted_analysis!$Q97>100,"Medium Value","Low Value")) -> Low Value | S97: Debit Card | T97: Delivered
... A110: ORD-1092 | B110: 45524 | C110: =TEXT(sorted_analysis!$B110,"MMMM") -> August | D110: Martha Sullivan | E110: martha.s@email.com | F110: West | G110: San Francisco | H110: Electronics | I110: Smart Doorbell | J110: 1 | K110: 179.99 | L110: =sorted_analysis!$K110*sorted_analysis!$J110 -> 179.99 | M110: 15 | N110: =sorted_analysis!$L110*(sorted_analysis!$M110/100) -> 26.9985 | O110: =sorted_analysis!$L110-sorted_analysis!$N110 -> 152.9915 | P110: 12.99 | Q110: =SUM(sorted_analysis!$O110+sorted_analysis!$P110) -> 165.9815 | R110: =IF(sorted_analysis!$Q110>200,"High Value",IF(sorted_analysis!$Q110>100,"Medium Value","Low Value")) -> Medium Value | S110: Credit Card | T110: Delivered
F111: West Count | Q111: =SUBTOTAL(3,Q86:Q110) -> 25
F112: West Total | Q112: =SUBTOTAL(9,Q86:Q110) -> 2192.3845
F113: West Average | Q113: =SUBTOTAL(1,Q86:Q110) -> 87.69538
F114: Grand Count | Q114: =SUBTOTAL(3,Q2:Q110) -> 100
F115: Grand Total | Q115: =SUBTOTAL(9,Q2:Q110) -> 8955.5195
F116: Grand Average | Q116: =SUBTOTAL(1,Q2:Q110) -> 89.555195

Sheet Region_Analysis
B3: Column Labels
B4: Cancelled | D4: Delivered | F4: Processing | H4: Total Sum of Total Order Value | I4: Total Count of Order_ID
A5: Row Labels | B5: Sum of Total Order Value | C5: Count of Order_ID | D5: Sum of Total Order Value | E5: Count of Order_ID | F5: Sum of Total Order Value | G5: Count of Order_ID
A6: North | B6: 149.895 | C6: 2 | D6: 1974.0175 | E6: 20 | F6: 252.909 | G6: 3 | H6: 2376.8215 | I6: 25
A7: South | B7: 121.4715 | C7: 1 | D7: 1806.537 | E7: 21 | F7: 196.1575 | G7: 3 | H7: 2124.166 | I7: 25
A8: East | B8: 185.943 | C8: 3 | D8: 1176.3565 | E8: 17 | F8: 899.848 | G8: 5 | H8: 2262.1475 | I8: 25
A9: West | B9: 53.939 | C9: 1 | D9: 1915.0005 | E9: 22 | F9: 223.445 | G9: 2 | H9: 2192.3845 | I9: 25
A10: Grand Total | B10: 511.2485 | C10: 7 | D10: 6871.9115 | E10: 80 | F10: 1572.3595 | G10: 13 | H10: 8955.5195 | I10: 100

Sheet Product_Analysis
A3: % of Column Total | B3: Column Labels
A4: Row Labels | B4: January | C4: February | D4: March | E4: April | F4: May | G4: June | H4: July | I4: August | J4: September | K4: Grand Total
A5: Books | B5: 0.17043251 | C5: 0.082633331 | D5: 0.17071946 | E5: 0.17709929 | F5: 0.11250532 | G5: 0.18846129 | H5: 0.20855415 | I5: 0.046970993 | J5: 0.25414614 | K5: 0.13941843
A6: Clothing | B6: 0.20921945 | C6: 0.21037523 | D6: 0.14168786 | E6: 0.30957546 | F6: 0.17352516 | G6: 0.1662791 | H6: 0.18503629 | I6: 0.14240466 | J6: 0.22316368 | K6: 0.18845903
A7: Electronics | B7: 0.45117759 | C7: 0.50397341 | D7: 0.38772837 | E7: 0.32196305 | F7: 0.40492037 | G7: 0.35423972 | H7: 0.44608264 | I7: 0.64852265 | J7: 0.38175371 | K7: 0.45652589
A8: Home & Garden | B8: 0.16917045 | C8: 0.20301803 | D8: 0.29986431 | E8: 0.1913622 | F8: 0.30904915 | G8: 0.29101989 | H8: 0.16032692 | I8: 0.16210171 | J8: 0.14093647 | K8: 0.21559665
A9: Grand Total | B9: 1 | C9: 1 | D9: 1 | E9: 1 | F9: 1 | G9: 1 | H9: 1 | I9: 1 | J9: 1 | K9: 1

Sheet Customer_Analysis
B3: Column Labels
B4: Cancelled | D4: Delivered | F4: Processing | H4: Total Count of Customer_Name | I4: Total Sum of Total Order Value
A5: Row Labels | B5: Count of Customer_Name | C5: Sum of Total Order Value | D5: Count of Customer_Name | E5: Sum of Total Order Value | F5: Count of Customer_Name | G5: Sum of Total Order Value
A6: High Value | D6: 3 | E6: 853.4445 | F6: 1 | G6: 474.981 | H6: 4 | I6: 1328.4255
A7: North | D7: 2 | E7: 625.963 | H7: 2 | I7: 625.963
A8: South | D8: 1 | E8: 227.4815 | H8: 1 | I8: 227.4815
A9: East | F9: 1 | G9: 474.981 | H9: 1 | I9: 474.981
A10: Low Value | B10: 6 | C10: 389.777 | D10: 60 | E10: 3899.8715 | F10: 10 | G10: 775.935 | H10: 76 | I10: 5065.5835
A11: North | B11: 2 | C11: 149.895 | D11: 15 | E11: 1000.611 | F11: 3 | G11: 252.909 | H11: 20 | I11: 1403.415
A12: South | D12: 16 | E12: 1087.6575 | F12: 3 | G12: 196.1575 | H12: 19 | I12: 1283.815
A13: East | B13: 3 | C13: 185.943 | D13: 14 | E13: 825.4405 | F13: 3 | G13: 243.8855 | H13: 20 | I13: 1255.269
A14: West | B14: 1 | C14: 53.939 | D14: 15 | E14: 986.1625 | F14: 1 | G14: 82.983 | H14: 17 | I14: 1123.0845
A15: Medium Value | B15: 1 | C15: 121.4715 | D15: 17 | E15: 2118.5955 | F15: 2 | G15: 321.4435 | H15: 20 | I15: 2561.5105
A16: North | D16: 3 | E16: 347.4435 | H16: 3 | I16: 347.4435
A17: South | B17: 1 | C17: 121.4715 | D17: 4 | E17: 491.398 | H17: 5 | I17: 612.8695
A18: East | D18: 3 | E18: 350.916 | F18: 1 | G18: 180.9815 | H18: 4 | I18: 531.8975
A19: West | D19: 7 | E19: 928.838 | F19: 1 | G19: 140.462 | H19: 8 | I19: 1069.3
A20: Grand Total | B20: 7 | C20: 511.2485 | D20: 80 | E20: 6871.9115 | F20: 13 | G20: 1572.3595 | H20: 100 | I20: 8955.5195

Sheet Product_Trends
A1: Product Trends | B1: January | C1: February | D1: March | E1: April | F1: May | G1: June | H1: July | I1: August | J1: September | K1: Total | L1: Trend
A2: Electronics | B2: =COUNTIFS(sales_data!$H:$H,"Electronics",sales_data!$C:$C,"January") -> 5 | C2: =COUNTIFS(sales_data!$H:$H,"Electronics",sales_data!$C:$C,"February") -> 4 | D2: =COUNTIFS(sales_data!$H:$H,"Electronics",sales_data!$C:$C,"March") -> 4 | E2: =COUNTIFS(sales_data!$H:$H,"Electronics",sales_data!$C:$C,"April") -> 4 | F2: =COUNTIFS(sales_data!$H:$H,"Electronics",sales_data!$C:$C,"May") -> 4 | G2: =COUNTIFS(sales_data!$H:$H,"Electronics",sales_data!$C:$C,"June") -> 4 | H2: =COUNTIFS(sales_data!$H:$H,"Electronics",sales_data!$C:$C,"July") -> 4 | I2: =COUNTIFS(sales_data!$H:$H,"Electronics",sales_data!$C:$C,"August") -> 4 | J2: =COUNTIFS(sales_data!$H:$H,"Electronics",sales_data!$C:$C,"September") -> 1 | K2: =SUM(B2:J2) -> 34
A3: Home & Garden | B3: =COUNTIFS(sales_data!$H:$H,"Home & Garden",sales_data!$C:$C,"January") -> 2 | C3: =COUNTIFS(sales_data!$H:$H,"Home & Garden",sales_data!$C:$C,"February") -> 3 | D3: =COUNTIFS(sales_data!$H:$H,"Home & Garden",sales_data!$C:$C,"March") -> 3 | E3: =COUNTIFS(sales_data!$H:$H,"Home & Garden",sales_data!$C:$C,"April") -> 2 | F3: =COUNTIFS(sales_data!$H:$H,"Home & Garden",sales_data!$C:$C,"May") -> 3 | G3: =COUNTIFS(sales_data!$H:$H,"Home & Garden",sales_data!$C:$C,"June") -> 3 | H3: =COUNTIFS(sales_data!$H:$H,"Home & Garden",sales_data!$C:$C,"July") -> 2 | I3: =COUNTIFS(sales_data!$H:$H,"Home & Garden",sales_data!$C:$C,"August") -> 3 | J3: =COUNTIFS(sales_data!$H:$H,"Home & Garden",sales_data!$C:$C,"September") -> 1 | K3: =SUM(B3:J3) -> 22
A4: Clothing | B4: =COUNTIFS(sales_data!$H:$H,"Clothing",sales_data!$C:$C,"January") -> 2 | C4: =COUNTIFS(sales_data!$H:$H,"Clothing",sales_data!$C:$C,"February") -> 3 | D4: =COUNTIFS(sales_data!$H:$H,"Clothing",sales_data!$C:$C,"March") -> 2 | E4: =COUNTIFS(sales_data!$H:$H,"Clothing",sales_data!$C:$C,"April") -> 3 | F4: =COUNTIFS(sales_data!$H:$H,"Clothing",sales_data!$C:$C,"May") -> 3 | G4: =COUNTIFS(sales_data!$H:$H,"Clothing",sales_data!$C:$C,"June") -> 2 | H4: =COUNTIFS(sales_data!$H:$H,"Clothing",sales_data!$C:$C,"July") -> 3 | I4: =COUNTIFS(sales_data!$H:$H,"Clothing",sales_data!$C:$C,"August") -> 3 | J4: =COUNTIFS(sales_data!$H:$H,"Clothing",sales_data!$C:$C,"September") -> 1 | K4: =SUM(B4:J4) -> 22
A5: Books | B5: =COUNTIFS(sales_data!$H:$H,"Books",sales_data!$C:$C,"January") -> 2 | C5: =COUNTIFS(sales_data!$H:$H,"Books",sales_data!$C:$C,"February") -> 2 | D5: =COUNTIFS(sales_data!$H:$H,"Books",sales_data!$C:$C,"March") -> 3 | E5: =COUNTIFS(sales_data!$H:$H,"Books",sales_data!$C:$C,"April") -> 3 | F5: =COUNTIFS(sales_data!$H:$H,"Books",sales_data!$C:$C,"May") -> 2 | G5: =COUNTIFS(sales_data!$H:$H,"Books",sales_data!$C:$C,"June") -> 3 | H5: =COUNTIFS(sales_data!$H:$H,"Books",sales_data!$C:$C,"July") -> 3 | I5: =COUNTIFS(sales_data!$H:$H,"Books",sales_data!$C:$C,"August") -> 2 | J5: =COUNTIFS(sales_data!$H:$H,"Books",sales_data!$C:$C,"September") -> 2 | K5: =SUM(B5:J5) -> 22
